Workbook

Sheet README
A1: SACCO Loan Delinquency & Collections Analytics — Excel Workbook
A2: United Winners DT SACCO, Nairobi -- SYNTHETIC demonstration data. Not United Winners' actual portfolio figures.
A3: Case-study organization: United Winners DT SACCO, Nairobi. This workbook is a demonstration analytics build using SYNTHETIC data -- it does not claim access to United Winners' internal data, and no figure in it should be presented as United Winners' actual performance.
A5: What This Workbook Is
A6: A working Excel implementation of the already-validated SQL analytics layer (schema.sql / business_queries.sql). Every KPI, table and chart in the analysis sheets is a LIVE formula over the embedded Dim_/Fact_ tables below -- nothing is pasted as a static number. All figures reconcile exactly to the validated SQL output.
A7: Correct framing for interviews and write-ups: “I researched a relevant SACCO-sector problem and built a working analytics demonstration using synthetic data to show how this approach could be applied to a SACCO such as United Winners.” Never: “I analyzed United Winners' portfolio” or “I discovered United Winners' delinquency problem.”
A9: Sheet Directory
A10: Sheet | B10: Contents
A11: KPI_Summary | B11: Headline portfolio-risk and collections-effectiveness KPIs (all live formulas).
A12: Product_Segment_Analysis | B12: Active loans, delinquency rate, PAR30, balance by product / segment / channel.
A13: Vintage_Analysis | B13: H3 seeded-weak-vintage pooled test + loan-age curve.
A14: Collections_Effectiveness | B14: Channel conversion & recovery-per-contact; recovery-source split.
A15: Q10_Savings_Behaviour | B15: Pre-delinquency savings-contribution comparison (treatment / matched / unmatched).
A16: Data_Quality | B16: Live referential-integrity, business-rule and uniqueness checks.
A17: Dim_Products / Dim_Members / Dim_Branches | B17: Dimension tables (13 / 353 / 3 rows).
A18: Fact_Loans | B18: One row per loan (650) -- dimensional attributes + product/segment/branch lookups.
A19: Fact_Snapshot_History | B19: One row per loan per month (5,853) -- the core fact table for all point-in-time and vintage analysis.
A20: Fact_Collections / Fact_Recovery | B20: Collections activity log (186) and recovery transactions (36).
A21: Fact_Collection_Cases / Fact_Arrears | B21: Already-derived, SQL-validated views: 6-month recovery cases (104), arrears-source detail (433).
A22: Fact_Q10 / Fact_Savings_Activity | B22: Already-derived Q10 comparison detail (5,738) and the full savings-activity log (13,308).
A24: Data Model Relationships
A25: From Table [Key] | B25: Relates To | C25: Cardinality
A26: Fact_Loans[product_id] | B26: Dim_Products[product_id] | C26: many-to-one
A27: Fact_Loans[member_id] | B27: Dim_Members[member_id] | C27: many-to-one
A28: Fact_Loans[branch_id] | B28: Dim_Branches[branch_id] | C28: many-to-one
A29: Fact_Snapshot_History[loan_id] | B29: Fact_Loans[loan_id] | C29: many-to-one
A30: Fact_Collections[loan_id] | B30: Fact_Loans[loan_id] | C30: many-to-one
A31: Fact_Recovery[loan_id] | B31: Fact_Loans[loan_id] | C31: many-to-one
A32: Fact_Recovery[related_activity_id] | B32: Fact_Collections[activity_id] | C32: many-to-one, nullable
A33: Fact_Collection_Cases[loan_id] | B33: Fact_Loans[loan_id] | C33: one-to-one
A34: Fact_Arrears[loan_id] | B34: Fact_Loans[loan_id] | C34: many-to-one
A35: Fact_Q10[member_id] / Fact_Savings_Activity[member_id] | B35: Dim_Members[member_id] | C35: many-to-one
A37: Locked Metric Definitions -- Do Not Change
A38: Metric | B38: Definition
A39: Loan Delinquency Rate | B39: Delinquent active loans / active loans -- OPERATIONAL measure (count-based).
A40: PAR30 / PAR60 / PAR90 | B40: Balance of loans >=30/60/90 days past due / gross outstanding loan portfolio -- FINANCIAL EXPOSURE measure (balance-weighted).
A41: Recovery Rate | B41: Recoveries within the defined 6-month case window / amount referred into the case during that same window.
A42: Active Loans | B42: Loans with a Fact_Snapshot_History row on the single latest snapshot date AND outstanding_balance_ksh > 0 -- NOT the same as Fact_Loans' own convenience fields (each loan's own last recorded update, not a uniform portfolio-wide cut).
A44: Build Spec — Power Query Cleaning (Excel Desktop)
A45: 1. Data > Get Data > From File > From Folder, pointed at the 16 exported CSVs (or From Database > ODBC for sacco_analytics.db directly). One query per table.
A46: 2. Set explicit data types per column -- especially Date on disbursement_date, snapshot_date, join_date and every *_date/period column (already done here in the pandas prep layer that built this workbook).
A47: 3. Members: Replace Values -- null employer_name -> "Not Captured" (already applied). This is a deliberately-present data-quality issue per schema.sql, not an error to hide.
A48: 4. Validate categorical columns (member_segment, employment_type, member_status, category, repayment_channel, classification, payment_status, channel, outcome, recovery_source) against the fixed value lists in schema.sql's CHECK constraints.
A49: 5. Merge Queries: Fact_Loans + Dim_Products on product_id, + Dim_Members on member_id, + Dim_Branches on branch_id (Left Outer) to pull name/segment/branch attributes -- already implemented here as INDEX/MATCH formulas on Fact_Loans and as materialized merge columns on Fact_Snapshot_History.
A50: 6. Close & Load To... → "Only Create Connection" + "Add this data to the Data Model" for every query, so relationships and DAX measures become available.
A52: Build Spec — Data Model / Power Pivot
A53: In Power Pivot > Diagram View, recreate the relationships listed above (all many-to-one into Fact_Loans / Dim_Members, single-direction filter). Mark a Calendar table as the official Date Table (Design > Mark as Date Table) if you load Calendar.csv, to unlock time-intelligence DAX (SAMEPERIODLASTYEAR, DATESYTD, etc.).
A55: DAX-Equivalent Measures
A56: Measure | B56: DAX (Power Pivot)
A57: Active Loans | B57: Active Loans := CALCULATE(COUNTROWS(Fact_Snapshot_History), Fact_Snapshot_History[snapshot_date]=[Latest Date], Fact_Snapshot_History[outstanding_balance_ksh]>0)
A58: Outstanding Balance | B58: Outstanding Balance := CALCULATE(SUM(Fact_Snapshot_History[outstanding_balance_ksh]), Fact_Snapshot_History[snapshot_date]=[Latest Date], Fact_Snapshot_History[outstanding_balance_ksh]>0)
A59: Loan Delinquency Rate | B59: Loan Delinquency Rate := DIVIDE(CALCULATE([Active Loans], Fact_Snapshot_History[par30_flag]=1), [Active Loans])
A60: PAR30 | B60: PAR30 := DIVIDE(CALCULATE([Outstanding Balance], Fact_Snapshot_History[par30_flag]=1), [Outstanding Balance])
A61: Recovery Rate | B61: Recovery Rate := DIVIDE(SUM(Fact_Collection_Cases[recovered_in_window_ksh]), SUM(Fact_Collection_Cases[referred_amount_ksh]))
A62: Recovery per Contact | B62: Recovery per Contact := DIVIDE(SUM(Fact_Collections[linked_recovery_ksh]), COUNTROWS(Fact_Collections))
A64: Build Spec — Native PivotTables (from the Data Model)
A65: Product & Segment: Rows = Product Name (or Member Segment); Values = [Active Loans], [Outstanding Balance], [PAR30]; Filter = Snapshot Date (Latest Date only).
A66: Vintage curve: Rows = Vintage Cohort (year-month of disbursement); Columns = Months on Book; Values = [PAR30] as a heat-mapped matrix (classic vintage triangle).
A67: Collections by channel: Rows = Channel; Values = Count of Activity ID, [Recovery per Contact], Average of a Payment-Received 0/1 flag (= conversion rate).
A68: Every PivotTable above is already implemented as an equivalent SUMIFS/COUNTIFS table on the corresponding analysis sheet, so this workbook is usable immediately without Power Pivot -- the steps above are for extending it into a fully native Power Pivot model.
A70: Source & Transparency Notes
A71: Dim_Products.rate_source_note flags each product's interest-rate figure as VERIFIED (the product catalogue and Salary Advance cap) or an explicit ASSUMPTION where the real rate is not publicly disclosed. Branches reflects United Winners' 3 real branches. Every other figure in this workbook is generated synthetic data (see generate_data.py, random.seed(42)) built to a demonstration scale -- not a projection of United Winners' actual membership, loan book or staffing.

Sheet KPI_Summary
A1: KPI Summary — Loan Portfolio & Collections
A2: United Winners DT SACCO, Nairobi -- SYNTHETIC demonstration data. Not United Winners' actual portfolio figures.
A3: All figures below are LIVE formulas computed from the embedded Dim/Fact tables -- change the source data and every KPI recalculates. Metric definitions are locked to the validated SQL layer (business_queries.sql).
A5: Latest snapshot date (data as-of): | B5: =MAX(Fact_Snapshot_History!B2:B5854) -> 46265
A7: Portfolio Risk KPIs
A8: Metric | B8: Value | C8: Definition / Notes
A9: Active Loans | B9: =COUNTIFS(Fact_Snapshot_History!$B$2:$B$5854,$B$5,Fact_Snapshot_History!$C$2:$C$5854,">0") -> 205 | C9: Loans with a snapshot on the latest date and outstanding balance > 0.
A10: Outstanding Balance (Ksh) | B10: =SUMIFS(Fact_Snapshot_History!$C$2:$C$5854,Fact_Snapshot_History!$B$2:$B$5854,$B$5,Fact_Snapshot_History!$C$2:$C$5854,">0") -> 27804490 | C10: Gross outstanding balance across active loans.
A11: Loan Delinquency Rate | B11: =COUNTIFS(Fact_Snapshot_History!$B$2:$B$5854,$B$5,Fact_Snapshot_History!$C$2:$C$5854,">0",Fact_Snapshot_History!$G$2:$G$5854,1)/$B$9 -> 0.082926829 | C11: Delinquent active loans / active loans -- OPERATIONAL measure (count-based).
A12: PAR30 | B12: =SUMIFS(Fact_Snapshot_History!$C$2:$C$5854,Fact_Snapshot_History!$B$2:$B$5854,$B$5,Fact_Snapshot_History!$C$2:$C$5854,">0",Fact_Snapshot_History!$G$2:$G$5854,1)/$B$10 -> 0.19518118 | C12: Balance >=30dpd / gross outstanding balance -- FINANCIAL EXPOSURE measure.
A13: PAR60 | B13: =SUMIFS(Fact_Snapshot_History!$C$2:$C$5854,Fact_Snapshot_History!$B$2:$B$5854,$B$5,Fact_Snapshot_History!$C$2:$C$5854,">0",Fact_Snapshot_History!$H$2:$H$5854,1)/$B$10 -> 0.12954658 | C13: Balance >=60dpd / gross outstanding balance.
A14: PAR90 | B14: =SUMIFS(Fact_Snapshot_History!$C$2:$C$5854,Fact_Snapshot_History!$B$2:$B$5854,$B$5,Fact_Snapshot_History!$C$2:$C$5854,">0",Fact_Snapshot_History!$I$2:$I$5854,1)/$B$10 -> 0.082377422 | C14: Balance >=90dpd / gross outstanding balance.
A16: Collections Effectiveness KPIs
A17: Metric | B17: Value | C17: Definition / Notes
A18: Collection Cases (6-mo window) | B18: =COUNT(Fact_Collection_Cases!$A$2:$A$105) -> 104 | C18: Loans whose balance first crossed 30dpd; each opens one 6-month case.
A19: Total Referred (Ksh) | B19: =SUM(Fact_Collection_Cases!$D$2:$D$105) -> 1857405.2 | C19: Sum of shortfalls referred into a case during its 6-month window.
A20: Total Recovered in Window (Ksh) | B20: =SUM(Fact_Collection_Cases!$E$2:$E$105) -> 416114.8 | C20: Recoveries applied within each case's 6-month window.
A21: Recovery Rate | B21: =$B$20/$B$19 -> 0.22403017 | C21: Recovered-in-window / referred-in-window (bounded <=100% by construction).
A22: Total Collections Contacts | B22: =COUNTA(Fact_Collections!$A$2:$A$187) -> 186 | C22: All logged collections activities (calls, SMS, visits, etc.).
A23: Contact→Payment Conversion | B23: =COUNTIF(Fact_Collections!$F$2:$F$187,"Payment Received")/$B$22 -> 0.15053763 | C23: Share of contacts whose outcome was Payment Received.
A24: Recovery per Contact (Ksh) | B24: =SUM(Fact_Collections!$G$2:$G$187)/$B$22 -> 2165.4095 | C24: Total recovered linked to a contact / total contacts.
A26: Arrears Source Split
A27: Metric | B27: Value | C27: Definition / Notes
A28: Employer/Check-off Shortfall | B28: =SUMIF(Fact_Arrears!$C$2:$C$434,"Employer/check-off remittance shortfall",Fact_Arrears!$D$2:$D$434)/SUM(Fact_Arrears!$D$2:$D$434) -> 0.2339535 | C28: Share of total arrears value from Check-Off loans where the employer under-remitted.
A29: Direct/Member-side Shortfall | B29: =SUMIF(Fact_Arrears!$C$2:$C$434,"Direct/member-side repayment shortfall",Fact_Arrears!$D$2:$D$434)/SUM(Fact_Arrears!$D$2:$D$434) -> 0.7660465 | C29: Share of total arrears value from missed/partial payments on non-check-off loans.
A31: See Product & Segment Analysis, Vintage Analysis, Collections Effectiveness and Q10 Savings Behaviour sheets for the full breakdowns behind these headline KPIs.

Sheet Product_Segment_Analysis
A1: Product, Segment & Channel Analysis
A2: United Winners DT SACCO, Nairobi -- SYNTHETIC demonstration data. Not United Winners' actual portfolio figures.
A3: Active-loan cut at the latest snapshot date (see KPI Summary). Delinquency Rate = count-based; PAR30 = balance-weighted -- both shown side by side, never conflated.
A5: By Loan Product
A6: Product ID | B6: Product Name | C6: Category | D6: Active Loans | E6: Delinquency Rate | F6: PAR30 % | G6: Outstanding Balance (Ksh)
A7: 1 | B7: =INDEX(Dim_Products!$B$2:$B$14,MATCH($A7,Dim_Products!$A$2:$A$14,0)) -> Salary Advance | C7: =INDEX(Dim_Products!$C$2:$C$14,MATCH($A7,Dim_Products!$A$2:$A$14,0)) -> FOSA | D7: =COUNTIFS(Fact_Snapshot_History!$B$2:$B$5854,KPI_Summary!$B$5,Fact_Snapshot_History!$C$2:$C$5854,">0",Fact_Snapshot_History!$K$2:$K$5854,$A7) -> 8 | E7: =IFERROR(COUNTIFS(Fact_Snapshot_History!$B$2:$B$5854,KPI_Summary!$B$5,Fact_Snapshot_History!$C$2:$C$5854,">0",Fact_Snapshot_History!$K$2:$K$5854,$A7,Fact_Snapshot_History!$G$2:$G$5854,1)/$D7,"") -> 0 | F7: =IFERROR(SUMIFS(Fact_Snapshot_History!$C$2:$C$5854,Fact_Snapshot_History!$B$2:$B$5854,KPI_Summary!$B$5,Fact_Snapshot_History!$C$2:$C$5854,">0",Fact_Snapshot_History!$K$2:$K$5854,$A7,Fact_Snapshot_History!$G$2:$G$5854,1)/SUMIFS(Fact_Snapshot_History!$C$2:$C$5854,Fact_Snapshot_History!$B$2:$B$5854,KPI_Summary!$B$5,Fact_Snapshot_History!$C$2:$C$5854,">0",Fact_Snapshot_History!$K$2:$K$5854,$A7),"") -> 0 | G7: =SUMIFS(Fact_Snapshot_History!$C$2:$C$5854,Fact_Snapshot_History!$B$2:$B$5854,KPI_Summary!$B$5,Fact_Snapshot_History!$C$2:$C$5854,">0",Fact_Snapshot_History!$K$2:$K$5854,$A7) -> 418933.33
A8: 2 | B8: =INDEX(Dim_Products!$B$2:$B$14,MATCH($A8,Dim_Products!$A$2:$A$14,0)) -> Jeki Loan | C8: =INDEX(Dim_Products!$C$2:$C$14,MATCH($A8,Dim_Products!$A$2:$A$14,0)) -> FOSA | D8: =COUNTIFS(Fact_Snapshot_History!$B$2:$B$5854,KPI_Summary!$B$5,Fact_Snapshot_History!$C$2:$C$5854,">0",Fact_Snapshot_History!$K$2:$K$5854,$A8) -> 19 | E8: =IFERROR(COUNTIFS(Fact_Snapshot_History!$B$2:$B$5854,KPI_Summary!$B$5,Fact_Snapshot_History!$C$2:$C$5854,">0",Fact_Snapshot_History!$K$2:$K$5854,$A8,Fact_Snapshot_History!$G$2:$G$5854,1)/$D8,"") -> 0.10526316 | F8: =IFERROR(SUMIFS(Fact_Snapshot_History!$C$2:$C$5854,Fact_Snapshot_History!$B$2:$B$5854,KPI_Summary!$B$5,Fact_Snapshot_History!$C$2:$C$5854,">0",Fact_Snapshot_History!$K$2:$K$5854,$A8,Fact_Snapshot_History!$G$2:$G$5854,1)/SUMIFS(Fact_Snapshot_History!$C$2:$C$5854,Fact_Snapshot_History!$B$2:$B$5854,KPI_Summary!$B$5,Fact_Snapshot_History!$C$2:$C$5854,">0",Fact_Snapshot_History!$K$2:$K$5854,$A8),"") -> 0.093689675 | G8: =SUMIFS(Fact_Snapshot_History!$C$2:$C$5854,Fact_Snapshot_History!$B$2:$B$5854,KPI_Summary!$B$5,Fact_Snapshot_History!$C$2:$C$5854,">0",Fact_Snapshot_History!$K$2:$K$5854,$A8) -> 365698.57
A9: 3 | B9: =INDEX(Dim_Products!$B$2:$B$14,MATCH($A9,Dim_Products!$A$2:$A$14,0)) -> Product Loan | C9: =INDEX(Dim_Products!$C$2:$C$14,MATCH($A9,Dim_Products!$A$2:$A$14,0)) -> FOSA | D9: =COUNTIFS(Fact_Snapshot_History!$B$2:$B$5854,KPI_Summary!$B$5,Fact_Snapshot_History!$C$2:$C$5854,">0",Fact_Snapshot_History!$K$2:$K$5854,$A9) -> 14 | E9: =IFERROR(COUNTIFS(Fact_Snapshot_History!$B$2:$B$5854,KPI_Summary!$B$5,Fact_Snapshot_History!$C$2:$C$5854,">0",Fact_Snapshot_History!$K$2:$K$5854,$A9,Fact_Snapshot_History!$G$2:$G$5854,1)/$D9,"") -> 0.071428571 | F9: =IFERROR(SUMIFS(Fact_Snapshot_History!$C$2:$C$5854,Fact_Snapshot_History!$B$2:$B$5854,KPI_Summary!$B$5,Fact_Snapshot_History!$C$2:$C$5854,">0",Fact_Snapshot_History!$K$2:$K$5854,$A9,Fact_Snapshot_History!$G$2:$G$5854,1)/SUMIFS(Fact_Snapshot_History!$C$2:$C$5854,Fact_Snapshot_History!$B$2:$B$5854,KPI_Summary!$B$5,Fact_Snapshot_History!$C$2:$C$5854,">0",Fact_Snapshot_History!$K$2:$K$5854,$A9),"") -> 0.061249136 | G9: =SUMIFS(Fact_Snapshot_History!$C$2:$C$5854,Fact_Snapshot_History!$B$2:$B$5854,KPI_Summary!$B$5,Fact_Snapshot_History!$C$2:$C$5854,">0",Fact_Snapshot_History!$K$2:$K$5854,$A9) -> 231393.14
A10: 4 | B10: =INDEX(Dim_Products!$B$2:$B$14,MATCH($A10,Dim_Products!$A$2:$A$14,0)) -> Mtumishi Loan | C10: =INDEX(Dim_Products!$C$2:$C$14,MATCH($A10,Dim_Products!$A$2:$A$14,0)) -> FOSA | D10: =COUNTIFS(Fact_Snapshot_History!$B$2:$B$5854,KPI_Summary!$B$5,Fact_Snapshot_History!$C$2:$C$5854,">0",Fact_Snapshot_History!$K$2:$K$5854,$A10) -> 10 | E10: =IFERROR(COUNTIFS(Fact_Snapshot_History!$B$2:$B$5854,KPI_Summary!$B$5,Fact_Snapshot_History!$C$2:$C$5854,">0",Fact_Snapshot_History!$K$2:$K$5854,$A10,Fact_Snapshot_History!$G$2:$G$5854,1)/$D10,"") -> 0 | F10: =IFERROR(SUMIFS(Fact_Snapshot_History!$C$2:$C$5854,Fact_Snapshot_History!$B$2:$B$5854,KPI_Summary!$B$5,Fact_Snapshot_History!$C$2:$C$5854,">0",Fact_Snapshot_History!$K$2:$K$5854,$A10,Fact_Snapshot_History!$G$2:$G$5854,1)/SUMIFS(Fact_Snapshot_History!$C$2:$C$5854,Fact_Snapshot_History!$B$2:$B$5854,KPI_Summary!$B$5,Fact_Snapshot_History!$C$2:$C$5854,">0",Fact_Snapshot_History!$K$2:$K$5854,$A10),"") -> 0 | G10: =SUMIFS(Fact_Snapshot_History!$C$2:$C$5854,Fact_Snapshot_History!$B$2:$B$5854,KPI_Summary!$B$5,Fact_Snapshot_History!$C$2:$C$5854,">0",Fact_Snapshot_History!$K$2:$K$5854,$A10) -> 522615.47
A11: 5 | B11: =INDEX(Dim_Products!$B$2:$B$14,MATCH($A11,Dim_Products!$A$2:$A$14,0)) -> School Fees Loan | C11: =INDEX(Dim_Products!$C$2:$C$14,MATCH($A11,Dim_Products!$A$2:$A$14,0)) -> BOSA | D11: =COUNTIFS(Fact_Snapshot_History!$B$2:$B$5854,KPI_Summary!$B$5,Fact_Snapshot_History!$C$2:$C$5854,">0",Fact_Snapshot_History!$K$2:$K$5854,$A11) -> 11 | E11: =IFERROR(COUNTIFS(Fact_Snapshot_History!$B$2:$B$5854,KPI_Summary!$B$5,Fact_Snapshot_History!$C$2:$C$5854,">0",Fact_Snapshot_History!$K$2:$K$5854,$A11,Fact_Snapshot_History!$G$2:$G$5854,1)/$D11,"") -> 0.090909091 | F11: =IFERROR(SUMIFS(Fact_Snapshot_History!$C$2:$C$5854,Fact_Snapshot_History!$B$2:$B$5854,KPI_Summary!$B$5,Fact_Snapshot_History!$C$2:$C$5854,">0",Fact_Snapshot_History!$K$2:$K$5854,$A11,Fact_Snapshot_History!$G$2:$G$5854,1)/SUMIFS(Fact_Snapshot_History!$C$2:$C$5854,Fact_Snapshot_History!$B$2:$B$5854,KPI_Summary!$B$5,Fact_Snapshot_History!$C$2:$C$5854,">0",Fact_Snapshot_History!$K$2:$K$5854,$A11),"") -> 0.088887065 | G11: =SUMIFS(Fact_Snapshot_History!$C$2:$C$5854,Fact_Snapshot_History!$B$2:$B$5854,KPI_Summary!$B$5,Fact_Snapshot_History!$C$2:$C$5854,">0",Fact_Snapshot_History!$K$2:$K$5854,$A11) -> 247488.54
A12: 6 | B12: =INDEX(Dim_Products!$B$2:$B$14,MATCH($A12,Dim_Products!$A$2:$A$14,0)) -> Bima Loan | C12: =INDEX(Dim_Products!$C$2:$C$14,MATCH($A12,Dim_Products!$A$2:$A$14,0)) -> BOSA | D12: =COUNTIFS(Fact_Snapshot_History!$B$2:$B$5854,KPI_Summary!$B$5,Fact_Snapshot_History!$C$2:$C$5854,">0",Fact_Snapshot_History!$K$2:$K$5854,$A12) -> 20 | E12: =IFERROR(COUNTIFS(Fact_Snapshot_History!$B$2:$B$5854,KPI_Summary!$B$5,Fact_Snapshot_History!$C$2:$C$5854,">0",Fact_Snapshot_History!$K$2:$K$5854,$A12,Fact_Snapshot_History!$G$2:$G$5854,1)/$D12,"") -> 0.1 | F12: =IFERROR(SUMIFS(Fact_Snapshot_History!$C$2:$C$5854,Fact_Snapshot_History!$B$2:$B$5854,KPI_Summary!$B$5,Fact_Snapshot_History!$C$2:$C$5854,">0",Fact_Snapshot_History!$K$2:$K$5854,$A12,Fact_Snapshot_History!$G$2:$G$5854,1)/SUMIFS(Fact_Snapshot_History!$C$2:$C$5854,Fact_Snapshot_History!$B$2:$B$5854,KPI_Summary!$B$5,Fact_Snapshot_History!$C$2:$C$5854,">0",Fact_Snapshot_History!$K$2:$K$5854,$A12),"") -> 0.089603105 | G12: =SUMIFS(Fact_Snapshot_History!$C$2:$C$5854,Fact_Snapshot_History!$B$2:$B$5854,KPI_Summary!$B$5,Fact_Snapshot_History!$C$2:$C$5854,">0",Fact_Snapshot_History!$K$2:$K$5854,$A12) -> 292044.79
A13: 7 | B13: =INDEX(Dim_Products!$B$2:$B$14,MATCH($A13,Dim_Products!$A$2:$A$14,0)) -> Development Loan | C13: =INDEX(Dim_Products!$C$2:$C$14,MATCH($A13,Dim_Products!$A$2:$A$14,0)) -> BOSA | D13: =COUNTIFS(Fact_Snapshot_History!$B$2:$B$5854,KPI_Summary!$B$5,Fact_Snapshot_History!$C$2:$C$5854,">0",Fact_Snapshot_History!$K$2:$K$5854,$A13) -> 21 | E13: =IFERROR(COUNTIFS(Fact_Snapshot_History!$B$2:$B$5854,KPI_Summary!$B$5,Fact_Snapshot_History!$C$2:$C$5854,">0",Fact_Snapshot_History!$K$2:$K$5854,$A13,Fact_Snapshot_History!$G$2:$G$5854,1)/$D13,"") -> 0.095238095 | F13: =IFERROR(SUMIFS(Fact_Snapshot_History!$C$2:$C$5854,Fact_Snapshot_History!$B$2:$B$5854,KPI_Summary!$B$5,Fact_Snapshot_History!$C$2:$C$5854,">0",Fact_Snapshot_History!$K$2:$K$5854,$A13,Fact_Snapshot_History!$G$2:$G$5854,1)/SUMIFS(Fact_Snapshot_History!$C$2:$C$5854,Fact_Snapshot_History!$B$2:$B$5854,KPI_Summary!$B$5,Fact_Snapshot_History!$C$2:$C$5854,">0",Fact_Snapshot_History!$K$2:$K$5854,$A13),"") -> 0.071778401 | G13: =SUMIFS(Fact_Snapshot_History!$C$2:$C$5854,Fact_Snapshot_History!$B$2:$B$5854,KPI_Summary!$B$5,Fact_Snapshot_History!$C$2:$C$5854,">0",Fact_Snapshot_History!$K$2:$K$5854,$A13) -> 2631556
A14: 8 | B14: =INDEX(Dim_Products!$B$2:$B$14,MATCH($A14,Dim_Products!$A$2:$A$14,0)) -> Emergency Loan | C14: =INDEX(Dim_Products!$C$2:$C$14,MATCH($A14,Dim_Products!$A$2:$A$14,0)) -> BOSA | D14: =COUNTIFS(Fact_Snapshot_History!$B$2:$B$5854,KPI_Summary!$B$5,Fact_Snapshot_History!$C$2:$C$5854,">0",Fact_Snapshot_History!$K$2:$K$5854,$A14) -> 11 | E14: =IFERROR(COUNTIFS(Fact_Snapshot_History!$B$2:$B$5854,KPI_Summary!$B$5,Fact_Snapshot_History!$C$2:$C$5854,">0",Fact_Snapshot_History!$K$2:$K$5854,$A14,Fact_Snapshot_History!$G$2:$G$5854,1)/$D14,"") -> 0 | F14: =IFERROR(SUMIFS(Fact_Snapshot_History!$C$2:$C$5854,Fact_Snapshot_History!$B$2:$B$5854,KPI_Summary!$B$5,Fact_Snapshot_History!$C$2:$C$5854,">0",Fact_Snapshot_History!$K$2:$K$5854,$A14,Fact_Snapshot_History!$G$2:$G$5854,1)/SUMIFS(Fact_Snapshot_History!$C$2:$C$5854,Fact_Snapshot_History!$B$2:$B$5854,KPI_Summary!$B$5,Fact_Snapshot_History!$C$2:$C$5854,">0",Fact_Snapshot_History!$K$2:$K$5854,$A14),"") -> 0 | G14: =SUMIFS(Fact_Snapshot_History!$C$2:$C$5854,Fact_Snapshot_History!$B$2:$B$5854,KPI_Summary!$B$5,Fact_Snapshot_History!$C$2:$C$5854,">0",Fact_Snapshot_History!$K$2:$K$5854,$A14) -> 66669.57
A15: 9 | B15: =INDEX(Dim_Products!$B$2:$B$14,MATCH($A15,Dim_Products!$A$2:$A$14,0)) -> Instant Loan | C15: =INDEX(Dim_Products!$C$2:$C$14,MATCH($A15,Dim_Products!$A$2:$A$14,0)) -> BOSA | D15: =COUNTIFS(Fact_Snapshot_History!$B$2:$B$5854,KPI_Summary!$B$5,Fact_Snapshot_History!$C$2:$C$5854,">0",Fact_Snapshot_History!$K$2:$K$5854,$A15) -> 12 | E15: =IFERROR(COUNTIFS(Fact_Snapshot_History!$B$2:$B$5854,KPI_Summary!$B$5,Fact_Snapshot_History!$C$2:$C$5854,">0",Fact_Snapshot_History!$K$2:$K$5854,$A15,Fact_Snapshot_History!$G$2:$G$5854,1)/$D15,"") -> 0 | F15: =IFERROR(SUMIFS(Fact_Snapshot_History!$C$2:$C$5854,Fact_Snapshot_History!$B$2:$B$5854,KPI_Summary!$B$5,Fact_Snapshot_History!$C$2:$C$5854,">0",Fact_Snapshot_History!$K$2:$K$5854,$A15,Fact_Snapshot_History!$G$2:$G$5854,1)/SUMIFS(Fact_Snapshot_History!$C$2:$C$5854,Fact_Snapshot_History!$B$2:$B$5854,KPI_Summary!$B$5,Fact_Snapshot_History!$C$2:$C$5854,">0",Fact_Snapshot_History!$K$2:$K$5854,$A15),"") -> 0 | G15: =SUMIFS(Fact_Snapshot_History!$C$2:$C$5854,Fact_Snapshot_History!$B$2:$B$5854,KPI_Summary!$B$5,Fact_Snapshot_History!$C$2:$C$5854,">0",Fact_Snapshot_History!$K$2:$K$5854,$A15) -> 81783.34
A16: 10 | B16: =INDEX(Dim_Products!$B$2:$B$14,MATCH($A16,Dim_Products!$A$2:$A$14,0)) -> ELoan | C16: =INDEX(Dim_Products!$C$2:$C$14,MATCH($A16,Dim_Products!$A$2:$A$14,0)) -> BOSA | D16: =COUNTIFS(Fact_Snapshot_History!$B$2:$B$5854,KPI_Summary!$B$5,Fact_Snapshot_History!$C$2:$C$5854,">0",Fact_Snapshot_History!$K$2:$K$5854,$A16) -> 14 | E16: =IFERROR(COUNTIFS(Fact_Snapshot_History!$B$2:$B$5854,KPI_Summary!$B$5,Fact_Snapshot_History!$C$2:$C$5854,">0",Fact_Snapshot_History!$K$2:$K$5854,$A16,Fact_Snapshot_History!$G$2:$G$5854,1)/$D16,"") -> 0.071428571 | F16: =IFERROR(SUMIFS(Fact_Snapshot_History!$C$2:$C$5854,Fact_Snapshot_History!$B$2:$B$5854,KPI_Summary!$B$5,Fact_Snapshot_History!$C$2:$C$5854,">0",Fact_Snapshot_History!$K$2:$K$5854,$A16,Fact_Snapshot_History!$G$2:$G$5854,1)/SUMIFS(Fact_Snapshot_History!$C$2:$C$5854,Fact_Snapshot_History!$B$2:$B$5854,KPI_Summary!$B$5,Fact_Snapshot_History!$C$2:$C$5854,">0",Fact_Snapshot_History!$K$2:$K$5854,$A16),"") -> 0.051046571 | G16: =SUMIFS(Fact_Snapshot_History!$C$2:$C$5854,Fact_Snapshot_History!$B$2:$B$5854,KPI_Summary!$B$5,Fact_Snapshot_History!$C$2:$C$5854,">0",Fact_Snapshot_History!$K$2:$K$5854,$A16) -> 266982.87
A17: 11 | B17: =INDEX(Dim_Products!$B$2:$B$14,MATCH($A17,Dim_Products!$A$2:$A$14,0)) -> Moto Gari Loan | C17: =INDEX(Dim_Products!$C$2:$C$14,MATCH($A17,Dim_Products!$A$2:$A$14,0)) -> BOSA | D17: =COUNTIFS(Fact_Snapshot_History!$B$2:$B$5854,KPI_Summary!$B$5,Fact_Snapshot_History!$C$2:$C$5854,">0",Fact_Snapshot_History!$K$2:$K$5854,$A17) -> 17 | E17: =IFERROR(COUNTIFS(Fact_Snapshot_History!$B$2:$B$5854,KPI_Summary!$B$5,Fact_Snapshot_History!$C$2:$C$5854,">0",Fact_Snapshot_History!$K$2:$K$5854,$A17,Fact_Snapshot_History!$G$2:$G$5854,1)/$D17,"") -> 0.17647059 | F17: =IFERROR(SUMIFS(Fact_Snapshot_History!$C$2:$C$5854,Fact_Snapshot_History!$B$2:$B$5854,KPI_Summary!$B$5,Fact_Snapshot_History!$C$2:$C$5854,">0",Fact_Snapshot_History!$K$2:$K$5854,$A17,Fact_Snapshot_History!$G$2:$G$5854,1)/SUMIFS(Fact_Snapshot_History!$C$2:$C$5854,Fact_Snapshot_History!$B$2:$B$5854,KPI_Summary!$B$5,Fact_Snapshot_History!$C$2:$C$5854,">0",Fact_Snapshot_History!$K$2:$K$5854,$A17),"") -> 0.28959484 | G17: =SUMIFS(Fact_Snapshot_History!$C$2:$C$5854,Fact_Snapshot_History!$B$2:$B$5854,KPI_Summary!$B$5,Fact_Snapshot_History!$C$2:$C$5854,">0",Fact_Snapshot_History!$K$2:$K$5854,$A17) -> 8266226.8
A18: 12 | B18: =INDEX(Dim_Products!$B$2:$B$14,MATCH($A18,Dim_Products!$A$2:$A$14,0)) -> Mjengo Loan | C18: =INDEX(Dim_Products!$C$2:$C$14,MATCH($A18,Dim_Products!$A$2:$A$14,0)) -> BOSA | D18: =COUNTIFS(Fact_Snapshot_History!$B$2:$B$5854,KPI_Summary!$B$5,Fact_Snapshot_History!$C$2:$C$5854,">0",Fact_Snapshot_History!$K$2:$K$5854,$A18) -> 21 | E18: =IFERROR(COUNTIFS(Fact_Snapshot_History!$B$2:$B$5854,KPI_Summary!$B$5,Fact_Snapshot_History!$C$2:$C$5854,">0",Fact_Snapshot_History!$K$2:$K$5854,$A18,Fact_Snapshot_History!$G$2:$G$5854,1)/$D18,"") -> 0.19047619 | F18: =IFERROR(SUMIFS(Fact_Snapshot_History!$C$2:$C$5854,Fact_Snapshot_History!$B$2:$B$5854,KPI_Summary!$B$5,Fact_Snapshot_History!$C$2:$C$5854,">0",Fact_Snapshot_History!$K$2:$K$5854,$A18,Fact_Snapshot_History!$G$2:$G$5854,1)/SUMIFS(Fact_Snapshot_History!$C$2:$C$5854,Fact_Snapshot_History!$B$2:$B$5854,KPI_Summary!$B$5,Fact_Snapshot_History!$C$2:$C$5854,">0",Fact_Snapshot_History!$K$2:$K$5854,$A18),"") -> 0.24343774 | G18: =SUMIFS(Fact_Snapshot_History!$C$2:$C$5854,Fact_Snapshot_History!$B$2:$B$5854,KPI_Summary!$B$5,Fact_Snapshot_History!$C$2:$C$5854,">0",Fact_Snapshot_History!$K$2:$K$5854,$A18) -> 9686200.6
A19: 13 | B19: =INDEX(Dim_Products!$B$2:$B$14,MATCH($A19,Dim_Products!$A$2:$A$14,0)) -> Supa Loan | C19: =INDEX(Dim_Products!$C$2:$C$14,MATCH($A19,Dim_Products!$A$2:$A$14,0)) -> BOSA | D19: =COUNTIFS(Fact_Snapshot_History!$B$2:$B$5854,KPI_Summary!$B$5,Fact_Snapshot_History!$C$2:$C$5854,">0",Fact_Snapshot_History!$K$2:$K$5854,$A19) -> 27 | E19: =IFERROR(COUNTIFS(Fact_Snapshot_History!$B$2:$B$5854,KPI_Summary!$B$5,Fact_Snapshot_History!$C$2:$C$5854,">0",Fact_Snapshot_History!$K$2:$K$5854,$A19,Fact_Snapshot_History!$G$2:$G$5854,1)/$D19,"") -> 0.037037037 | F19: =IFERROR(SUMIFS(Fact_Snapshot_History!$C$2:$C$5854,Fact_Snapshot_History!$B$2:$B$5854,KPI_Summary!$B$5,Fact_Snapshot_History!$C$2:$C$5854,">0",Fact_Snapshot_History!$K$2:$K$5854,$A19,Fact_Snapshot_History!$G$2:$G$5854,1)/SUMIFS(Fact_Snapshot_History!$C$2:$C$5854,Fact_Snapshot_History!$B$2:$B$5854,KPI_Summary!$B$5,Fact_Snapshot_History!$C$2:$C$5854,">0",Fact_Snapshot_History!$K$2:$K$5854,$A19),"") -> 0.079534372 | G19: =SUMIFS(Fact_Snapshot_History!$C$2:$C$5854,Fact_Snapshot_History!$B$2:$B$5854,KPI_Summary!$B$5,Fact_Snapshot_History!$C$2:$C$5854,">0",Fact_Snapshot_History!$K$2:$K$5854,$A19) -> 4726897.1
A21: By Member Segment
B22: Member Segment | D22: Active Loans | E22: Delinquency Rate | F22: PAR30 % | G22: Outstanding Balance (Ksh)
B23: Individual | D23: =COUNTIFS(Fact_Snapshot_History!$B$2:$B$5854,KPI_Summary!$B$5,Fact_Snapshot_History!$C$2:$C$5854,">0",Fact_Snapshot_History!$N$2:$N$5854,"Individual") -> 127 | E23: =IFERROR(COUNTIFS(Fact_Snapshot_History!$B$2:$B$5854,KPI_Summary!$B$5,Fact_Snapshot_History!$C$2:$C$5854,">0",Fact_Snapshot_History!$N$2:$N$5854,"Individual",Fact_Snapshot_History!$G$2:$G$5854,1)/$D23,"") -> 0.039370079 | F23: =IFERROR(SUMIFS(Fact_Snapshot_History!$C$2:$C$5854,Fact_Snapshot_History!$B$2:$B$5854,KPI_Summary!$B$5,Fact_Snapshot_History!$C$2:$C$5854,">0",Fact_Snapshot_History!$N$2:$N$5854,"Individual",Fact_Snapshot_History!$G$2:$G$5854,1)/SUMIFS(Fact_Snapshot_History!$C$2:$C$5854,Fact_Snapshot_History!$B$2:$B$5854,KPI_Summary!$B$5,Fact_Snapshot_History!$C$2:$C$5854,">0",Fact_Snapshot_History!$N$2:$N$5854,"Individual"),"") -> 0.069659125 | G23: =SUMIFS(Fact_Snapshot_History!$C$2:$C$5854,Fact_Snapshot_History!$B$2:$B$5854,KPI_Summary!$B$5,Fact_Snapshot_History!$C$2:$C$5854,">0",Fact_Snapshot_History!$N$2:$N$5854,"Individual") -> 15685703
B24: SME | D24: =COUNTIFS(Fact_Snapshot_History!$B$2:$B$5854,KPI_Summary!$B$5,Fact_Snapshot_History!$C$2:$C$5854,">0",Fact_Snapshot_History!$N$2:$N$5854,"SME") -> 39 | E24: =IFERROR(COUNTIFS(Fact_Snapshot_History!$B$2:$B$5854,KPI_Summary!$B$5,Fact_Snapshot_History!$C$2:$C$5854,">0",Fact_Snapshot_History!$N$2:$N$5854,"SME",Fact_Snapshot_History!$G$2:$G$5854,1)/$D24,"") -> 0.12820513 | F24: =IFERROR(SUMIFS(Fact_Snapshot_History!$C$2:$C$5854,Fact_Snapshot_History!$B$2:$B$5854,KPI_Summary!$B$5,Fact_Snapshot_History!$C$2:$C$5854,">0",Fact_Snapshot_History!$N$2:$N$5854,"SME",Fact_Snapshot_History!$G$2:$G$5854,1)/SUMIFS(Fact_Snapshot_History!$C$2:$C$5854,Fact_Snapshot_History!$B$2:$B$5854,KPI_Summary!$B$5,Fact_Snapshot_History!$C$2:$C$5854,">0",Fact_Snapshot_History!$N$2:$N$5854,"SME"),"") -> 0.18364286 | G24: =SUMIFS(Fact_Snapshot_History!$C$2:$C$5854,Fact_Snapshot_History!$B$2:$B$5854,KPI_Summary!$B$5,Fact_Snapshot_History!$C$2:$C$5854,">0",Fact_Snapshot_History!$N$2:$N$5854,"SME") -> 7261863
B25: Corporate | D25: =COUNTIFS(Fact_Snapshot_History!$B$2:$B$5854,KPI_Summary!$B$5,Fact_Snapshot_History!$C$2:$C$5854,">0",Fact_Snapshot_History!$N$2:$N$5854,"Corporate") -> 13 | E25: =IFERROR(COUNTIFS(Fact_Snapshot_History!$B$2:$B$5854,KPI_Summary!$B$5,Fact_Snapshot_History!$C$2:$C$5854,">0",Fact_Snapshot_History!$N$2:$N$5854,"Corporate",Fact_Snapshot_History!$G$2:$G$5854,1)/$D25,"") -> 0.30769231 | F25: =IFERROR(SUMIFS(Fact_Snapshot_History!$C$2:$C$5854,Fact_Snapshot_History!$B$2:$B$5854,KPI_Summary!$B$5,Fact_Snapshot_History!$C$2:$C$5854,">0",Fact_Snapshot_History!$N$2:$N$5854,"Corporate",Fact_Snapshot_History!$G$2:$G$5854,1)/SUMIFS(Fact_Snapshot_History!$C$2:$C$5854,Fact_Snapshot_History!$B$2:$B$5854,KPI_Summary!$B$5,Fact_Snapshot_History!$C$2:$C$5854,">0",Fact_Snapshot_History!$N$2:$N$5854,"Corporate"),"") -> 0.75666843 | G25: =SUMIFS(Fact_Snapshot_History!$C$2:$C$5854,Fact_Snapshot_History!$B$2:$B$5854,KPI_Summary!$B$5,Fact_Snapshot_History!$C$2:$C$5854,">0",Fact_Snapshot_History!$N$2:$N$5854,"Corporate") -> 2206820.7
B26: Learning Institution | D26: =COUNTIFS(Fact_Snapshot_History!$B$2:$B$5854,KPI_Summary!$B$5,Fact_Snapshot_History!$C$2:$C$5854,">0",Fact_Snapshot_History!$N$2:$N$5854,"Learning Institution") -> 8 | E26: =IFERROR(COUNTIFS(Fact_Snapshot_History!$B$2:$B$5854,KPI_Summary!$B$5,Fact_Snapshot_History!$C$2:$C$5854,">0",Fact_Snapshot_History!$N$2:$N$5854,"Learning Institution",Fact_Snapshot_History!$G$2:$G$5854,1)/$D26,"") -> 0 | F26: =IFERROR(SUMIFS(Fact_Snapshot_History!$C$2:$C$5854,Fact_Snapshot_History!$B$2:$B$5854,KPI_Summary!$B$5,Fact_Snapshot_History!$C$2:$C$5854,">0",Fact_Snapshot_History!$N$2:$N$5854,"Learning Institution",Fact_Snapshot_History!$G$2:$G$5854,1)/SUMIFS(Fact_Snapshot_History!$C$2:$C$5854,Fact_Snapshot_History!$B$2:$B$5854,KPI_Summary!$B$5,Fact_Snapshot_History!$C$2:$C$5854,">0",Fact_Snapshot_History!$N$2:$N$5854,"Learning Institution"),"") -> 0 | G26: =SUMIFS(Fact_Snapshot_History!$C$2:$C$5854,Fact_Snapshot_History!$B$2:$B$5854,KPI_Summary!$B$5,Fact_Snapshot_History!$C$2:$C$5854,">0",Fact_Snapshot_History!$N$2:$N$5854,"Learning Institution") -> 213180.78
B27: Religious Institution | D27: =COUNTIFS(Fact_Snapshot_History!$B$2:$B$5854,KPI_Summary!$B$5,Fact_Snapshot_History!$C$2:$C$5854,">0",Fact_Snapshot_History!$N$2:$N$5854,"Religious Institution") -> 18 | E27: =IFERROR(COUNTIFS(Fact_Snapshot_History!$B$2:$B$5854,KPI_Summary!$B$5,Fact_Snapshot_History!$C$2:$C$5854,">0",Fact_Snapshot_History!$N$2:$N$5854,"Religious Institution",Fact_Snapshot_History!$G$2:$G$5854,1)/$D27,"") -> 0.16666667 | F27: =IFERROR(SUMIFS(Fact_Snapshot_History!$C$2:$C$5854,Fact_Snapshot_History!$B$2:$B$5854,KPI_Summary!$B$5,Fact_Snapshot_History!$C$2:$C$5854,">0",Fact_Snapshot_History!$N$2:$N$5854,"Religious Institution",Fact_Snapshot_History!$G$2:$G$5854,1)/SUMIFS(Fact_Snapshot_History!$C$2:$C$5854,Fact_Snapshot_History!$B$2:$B$5854,KPI_Summary!$B$5,Fact_Snapshot_History!$C$2:$C$5854,">0",Fact_Snapshot_History!$N$2:$N$5854,"Religious Institution"),"") -> 0.54611501 | G27: =SUMIFS(Fact_Snapshot_History!$C$2:$C$5854,Fact_Snapshot_History!$B$2:$B$5854,KPI_Summary!$B$5,Fact_Snapshot_History!$C$2:$C$5854,">0",Fact_Snapshot_History!$N$2:$N$5854,"Religious Institution") -> 2436922.3
A29: By Repayment Channel
B30: Repayment Channel | D30: Active Loans | E30: Delinquency Rate | F30: PAR30 % | G30: Outstanding Balance (Ksh)
B31: Check-Off | D31: =COUNTIFS(Fact_Snapshot_History!$B$2:$B$5854,KPI_Summary!$B$5,Fact_Snapshot_History!$C$2:$C$5854,">0",Fact_Snapshot_History!$M$2:$M$5854,"Check-Off") -> 81 | E31: =IFERROR(COUNTIFS(Fact_Snapshot_History!$B$2:$B$5854,KPI_Summary!$B$5,Fact_Snapshot_History!$C$2:$C$5854,">0",Fact_Snapshot_History!$M$2:$M$5854,"Check-Off",Fact_Snapshot_History!$G$2:$G$5854,1)/$D31,"") -> 0.049382716 | F31: =IFERROR(SUMIFS(Fact_Snapshot_History!$C$2:$C$5854,Fact_Snapshot_History!$B$2:$B$5854,KPI_Summary!$B$5,Fact_Snapshot_History!$C$2:$C$5854,">0",Fact_Snapshot_History!$M$2:$M$5854,"Check-Off",Fact_Snapshot_History!$G$2:$G$5854,1)/SUMIFS(Fact_Snapshot_History!$C$2:$C$5854,Fact_Snapshot_History!$B$2:$B$5854,KPI_Summary!$B$5,Fact_Snapshot_History!$C$2:$C$5854,">0",Fact_Snapshot_History!$M$2:$M$5854,"Check-Off"),"") -> 0.16203734 | G31: =SUMIFS(Fact_Snapshot_History!$C$2:$C$5854,Fact_Snapshot_History!$B$2:$B$5854,KPI_Summary!$B$5,Fact_Snapshot_History!$C$2:$C$5854,">0",Fact_Snapshot_History!$M$2:$M$5854,"Check-Off") -> 10481574
B32: Direct-Standing-Order | D32: =COUNTIFS(Fact_Snapshot_History!$B$2:$B$5854,KPI_Summary!$B$5,Fact_Snapshot_History!$C$2:$C$5854,">0",Fact_Snapshot_History!$M$2:$M$5854,"Direct-Standing-Order") -> 71 | E32: =IFERROR(COUNTIFS(Fact_Snapshot_History!$B$2:$B$5854,KPI_Summary!$B$5,Fact_Snapshot_History!$C$2:$C$5854,">0",Fact_Snapshot_History!$M$2:$M$5854,"Direct-Standing-Order",Fact_Snapshot_History!$G$2:$G$5854,1)/$D32,"") -> 0.098591549 | F32: =IFERROR(SUMIFS(Fact_Snapshot_History!$C$2:$C$5854,Fact_Snapshot_History!$B$2:$B$5854,KPI_Summary!$B$5,Fact_Snapshot_History!$C$2:$C$5854,">0",Fact_Snapshot_History!$M$2:$M$5854,"Direct-Standing-Order",Fact_Snapshot_History!$G$2:$G$5854,1)/SUMIFS(Fact_Snapshot_History!$C$2:$C$5854,Fact_Snapshot_History!$B$2:$B$5854,KPI_Summary!$B$5,Fact_Snapshot_History!$C$2:$C$5854,">0",Fact_Snapshot_History!$M$2:$M$5854,"Direct-Standing-Order"),"") -> 0.099413904 | G32: =SUMIFS(Fact_Snapshot_History!$C$2:$C$5854,Fact_Snapshot_History!$B$2:$B$5854,KPI_Summary!$B$5,Fact_Snapshot_History!$C$2:$C$5854,">0",Fact_Snapshot_History!$M$2:$M$5854,"Direct-Standing-Order") -> 9928852.9
B33: Cash-MobileMoney | D33: =COUNTIFS(Fact_Snapshot_History!$B$2:$B$5854,KPI_Summary!$B$5,Fact_Snapshot_History!$C$2:$C$5854,">0",Fact_Snapshot_History!$M$2:$M$5854,"Cash-MobileMoney") -> 53 | E33: =IFERROR(COUNTIFS(Fact_Snapshot_History!$B$2:$B$5854,KPI_Summary!$B$5,Fact_Snapshot_History!$C$2:$C$5854,">0",Fact_Snapshot_History!$M$2:$M$5854,"Cash-MobileMoney",Fact_Snapshot_History!$G$2:$G$5854,1)/$D33,"") -> 0.11320755 | F33: =IFERROR(SUMIFS(Fact_Snapshot_History!$C$2:$C$5854,Fact_Snapshot_History!$B$2:$B$5854,KPI_Summary!$B$5,Fact_Snapshot_History!$C$2:$C$5854,">0",Fact_Snapshot_History!$M$2:$M$5854,"Cash-MobileMoney",Fact_Snapshot_History!$G$2:$G$5854,1)/SUMIFS(Fact_Snapshot_History!$C$2:$C$5854,Fact_Snapshot_History!$B$2:$B$5854,KPI_Summary!$B$5,Fact_Snapshot_History!$C$2:$C$5854,">0",Fact_Snapshot_History!$M$2:$M$5854,"Cash-MobileMoney"),"") -> 0.37076242 | G33: =SUMIFS(Fact_Snapshot_History!$C$2:$C$5854,Fact_Snapshot_History!$B$2:$B$5854,KPI_Summary!$B$5,Fact_Snapshot_History!$C$2:$C$5854,">0",Fact_Snapshot_History!$M$2:$M$5854,"Cash-MobileMoney") -> 7394062.8

Sheet Vintage_Analysis
A1: Vintage Analysis — Seeded Weak Cohort (H3)
A2: United Winners DT SACCO, Nairobi -- SYNTHETIC demonstration data. Not United Winners' actual portfolio figures.
A3: H3 (seeded on purpose, per the Hypothesis Register): loans disbursed Jan-Apr 2025 were seeded to perform worse as they age. Tested across each loan's full observed history (not one calendar month) -- matching the validated SQL vintage methodology exactly.
A5: Pooled Comparison (primary, most robust)
A6: Cohort Group | B6: Loan-Months (n) | C6: Delinquency Rate | D6: PAR30 %
A7: Seeded Weak Vintage (disbursed Jan-Apr 2025) | B7: =COUNTIF(Fact_Snapshot_History!$R$2:$R$5854,1) -> 372 | C7: =COUNTIFS(Fact_Snapshot_History!$R$2:$R$5854,1,Fact_Snapshot_History!$G$2:$G$5854,1)/B7 -> 0.077956989 | D7: =SUMIFS(Fact_Snapshot_History!$C$2:$C$5854,Fact_Snapshot_History!$R$2:$R$5854,1,Fact_Snapshot_History!$G$2:$G$5854,1)/SUMIFS(Fact_Snapshot_History!$C$2:$C$5854,Fact_Snapshot_History!$R$2:$R$5854,1) -> 0.025155114
A8: Other Cohorts (all other disbursement months) | B8: =COUNTIF(Fact_Snapshot_History!$R$2:$R$5854,0) -> 5481 | C8: =COUNTIFS(Fact_Snapshot_History!$R$2:$R$5854,0,Fact_Snapshot_History!$G$2:$G$5854,1)/B8 -> 0.047254151 | D8: =SUMIFS(Fact_Snapshot_History!$C$2:$C$5854,Fact_Snapshot_History!$R$2:$R$5854,0,Fact_Snapshot_History!$G$2:$G$5854,1)/SUMIFS(Fact_Snapshot_History!$C$2:$C$5854,Fact_Snapshot_History!$R$2:$R$5854,0) -> 0.037857283
A10: Reading this: the seeded cohort shows a higher count-based Delinquency Rate (more small loans go delinquent) alongside a lower balance-weighted PAR30 -- exactly the operational-vs-financial-exposure distinction this project treats as two separate, non-interchangeable metric families (see README).
A12: Vintage Curve by Loan Age (secondary, illustrative)
A13: Months on Book | B13: Seeded: n | C13: Seeded: PAR30 % | D13: Other: n | E13: Other: PAR30 %
A14: 0-2 | B14: =COUNTIFS(Fact_Snapshot_History!$P$2:$P$5854,">=0",Fact_Snapshot_History!$P$2:$P$5854,"<=2",Fact_Snapshot_History!$R$2:$R$5854,1) -> 126 | C14: =IFERROR(SUMIFS(Fact_Snapshot_History!$C$2:$C$5854,Fact_Snapshot_History!$P$2:$P$5854,">=0",Fact_Snapshot_History!$P$2:$P$5854,"<=2",Fact_Snapshot_History!$R$2:$R$5854,1,Fact_Snapshot_History!$G$2:$G$5854,1)/SUMIFS(Fact_Snapshot_History!$C$2:$C$5854,Fact_Snapshot_History!$P$2:$P$5854,">=0",Fact_Snapshot_History!$P$2:$P$5854,"<=2",Fact_Snapshot_History!$R$2:$R$5854,1),"") -> 0.0001266926 | D14: =COUNTIFS(Fact_Snapshot_History!$P$2:$P$5854,">=0",Fact_Snapshot_History!$P$2:$P$5854,"<=2",Fact_Snapshot_History!$R$2:$R$5854,0) -> 1685 | E14: =IFERROR(SUMIFS(Fact_Snapshot_History!$C$2:$C$5854,Fact_Snapshot_History!$P$2:$P$5854,">=0",Fact_Snapshot_History!$P$2:$P$5854,"<=2",Fact_Snapshot_History!$R$2:$R$5854,0,Fact_Snapshot_History!$G$2:$G$5854,1)/SUMIFS(Fact_Snapshot_History!$C$2:$C$5854,Fact_Snapshot_History!$P$2:$P$5854,">=0",Fact_Snapshot_History!$P$2:$P$5854,"<=2",Fact_Snapshot_History!$R$2:$R$5854,0),"") -> 0
A15: 3-5 | B15: =COUNTIFS(Fact_Snapshot_History!$P$2:$P$5854,">=3",Fact_Snapshot_History!$P$2:$P$5854,"<=5",Fact_Snapshot_History!$R$2:$R$5854,1) -> 81 | C15: =IFERROR(SUMIFS(Fact_Snapshot_History!$C$2:$C$5854,Fact_Snapshot_History!$P$2:$P$5854,">=3",Fact_Snapshot_History!$P$2:$P$5854,"<=5",Fact_Snapshot_History!$R$2:$R$5854,1,Fact_Snapshot_History!$G$2:$G$5854,1)/SUMIFS(Fact_Snapshot_History!$C$2:$C$5854,Fact_Snapshot_History!$P$2:$P$5854,">=3",Fact_Snapshot_History!$P$2:$P$5854,"<=5",Fact_Snapshot_History!$R$2:$R$5854,1),"") -> 0.012205026 | D15: =COUNTIFS(Fact_Snapshot_History!$P$2:$P$5854,">=3",Fact_Snapshot_History!$P$2:$P$5854,"<=5",Fact_Snapshot_History!$R$2:$R$5854,0) -> 1164 | E15: =IFERROR(SUMIFS(Fact_Snapshot_History!$C$2:$C$5854,Fact_Snapshot_History!$P$2:$P$5854,">=3",Fact_Snapshot_History!$P$2:$P$5854,"<=5",Fact_Snapshot_History!$R$2:$R$5854,0,Fact_Snapshot_History!$G$2:$G$5854,1)/SUMIFS(Fact_Snapshot_History!$C$2:$C$5854,Fact_Snapshot_History!$P$2:$P$5854,">=3",Fact_Snapshot_History!$P$2:$P$5854,"<=5",Fact_Snapshot_History!$R$2:$R$5854,0),"") -> 0.047737131
A16: 6-8 | B16: =COUNTIFS(Fact_Snapshot_History!$P$2:$P$5854,">=6",Fact_Snapshot_History!$P$2:$P$5854,"<=8",Fact_Snapshot_History!$R$2:$R$5854,1) -> 50 | C16: =IFERROR(SUMIFS(Fact_Snapshot_History!$C$2:$C$5854,Fact_Snapshot_History!$P$2:$P$5854,">=6",Fact_Snapshot_History!$P$2:$P$5854,"<=8",Fact_Snapshot_History!$R$2:$R$5854,1,Fact_Snapshot_History!$G$2:$G$5854,1)/SUMIFS(Fact_Snapshot_History!$C$2:$C$5854,Fact_Snapshot_History!$P$2:$P$5854,">=6",Fact_Snapshot_History!$P$2:$P$5854,"<=8",Fact_Snapshot_History!$R$2:$R$5854,1),"") -> 0.070429429 | D16: =COUNTIFS(Fact_Snapshot_History!$P$2:$P$5854,">=6",Fact_Snapshot_History!$P$2:$P$5854,"<=8",Fact_Snapshot_History!$R$2:$R$5854,0) -> 689 | E16: =IFERROR(SUMIFS(Fact_Snapshot_History!$C$2:$C$5854,Fact_Snapshot_History!$P$2:$P$5854,">=6",Fact_Snapshot_History!$P$2:$P$5854,"<=8",Fact_Snapshot_History!$R$2:$R$5854,0,Fact_Snapshot_History!$G$2:$G$5854,1)/SUMIFS(Fact_Snapshot_History!$C$2:$C$5854,Fact_Snapshot_History!$P$2:$P$5854,">=6",Fact_Snapshot_History!$P$2:$P$5854,"<=8",Fact_Snapshot_History!$R$2:$R$5854,0),"") -> 0.06156658
A17: 9-12 | B17: =COUNTIFS(Fact_Snapshot_History!$P$2:$P$5854,">=9",Fact_Snapshot_History!$P$2:$P$5854,"<=12",Fact_Snapshot_History!$R$2:$R$5854,1) -> 63 | C17: =IFERROR(SUMIFS(Fact_Snapshot_History!$C$2:$C$5854,Fact_Snapshot_History!$P$2:$P$5854,">=9",Fact_Snapshot_History!$P$2:$P$5854,"<=12",Fact_Snapshot_History!$R$2:$R$5854,1,Fact_Snapshot_History!$G$2:$G$5854,1)/SUMIFS(Fact_Snapshot_History!$C$2:$C$5854,Fact_Snapshot_History!$P$2:$P$5854,">=9",Fact_Snapshot_History!$P$2:$P$5854,"<=12",Fact_Snapshot_History!$R$2:$R$5854,1),"") -> 0.059009263 | D17: =COUNTIFS(Fact_Snapshot_History!$P$2:$P$5854,">=9",Fact_Snapshot_History!$P$2:$P$5854,"<=12",Fact_Snapshot_History!$R$2:$R$5854,0) -> 663 | E17: =IFERROR(SUMIFS(Fact_Snapshot_History!$C$2:$C$5854,Fact_Snapshot_History!$P$2:$P$5854,">=9",Fact_Snapshot_History!$P$2:$P$5854,"<=12",Fact_Snapshot_History!$R$2:$R$5854,0,Fact_Snapshot_History!$G$2:$G$5854,1)/SUMIFS(Fact_Snapshot_History!$C$2:$C$5854,Fact_Snapshot_History!$P$2:$P$5854,">=9",Fact_Snapshot_History!$P$2:$P$5854,"<=12",Fact_Snapshot_History!$R$2:$R$5854,0),"") -> 0.065169274
A18: 13-24 | B18: =COUNTIFS(Fact_Snapshot_History!$P$2:$P$5854,">=13",Fact_Snapshot_History!$P$2:$P$5854,"<=24",Fact_Snapshot_History!$R$2:$R$5854,1) -> 52 | C18: =IFERROR(SUMIFS(Fact_Snapshot_History!$C$2:$C$5854,Fact_Snapshot_History!$P$2:$P$5854,">=13",Fact_Snapshot_History!$P$2:$P$5854,"<=24",Fact_Snapshot_History!$R$2:$R$5854,1,Fact_Snapshot_History!$G$2:$G$5854,1)/SUMIFS(Fact_Snapshot_History!$C$2:$C$5854,Fact_Snapshot_History!$P$2:$P$5854,">=13",Fact_Snapshot_History!$P$2:$P$5854,"<=24",Fact_Snapshot_History!$R$2:$R$5854,1),"") -> 0.0010582416 | D18: =COUNTIFS(Fact_Snapshot_History!$P$2:$P$5854,">=13",Fact_Snapshot_History!$P$2:$P$5854,"<=24",Fact_Snapshot_History!$R$2:$R$5854,0) -> 837 | E18: =IFERROR(SUMIFS(Fact_Snapshot_History!$C$2:$C$5854,Fact_Snapshot_History!$P$2:$P$5854,">=13",Fact_Snapshot_History!$P$2:$P$5854,"<=24",Fact_Snapshot_History!$R$2:$R$5854,0,Fact_Snapshot_History!$G$2:$G$5854,1)/SUMIFS(Fact_Snapshot_History!$C$2:$C$5854,Fact_Snapshot_History!$P$2:$P$5854,">=13",Fact_Snapshot_History!$P$2:$P$5854,"<=24",Fact_Snapshot_History!$R$2:$R$5854,0),"") -> 0.039109474
A19: 25+ | B19: =COUNTIFS(Fact_Snapshot_History!$P$2:$P$5854,">=25",Fact_Snapshot_History!$P$2:$P$5854,"<=999",Fact_Snapshot_History!$R$2:$R$5854,1) -> 0 | C19: =IFERROR(SUMIFS(Fact_Snapshot_History!$C$2:$C$5854,Fact_Snapshot_History!$P$2:$P$5854,">=25",Fact_Snapshot_History!$P$2:$P$5854,"<=999",Fact_Snapshot_History!$R$2:$R$5854,1,Fact_Snapshot_History!$G$2:$G$5854,1)/SUMIFS(Fact_Snapshot_History!$C$2:$C$5854,Fact_Snapshot_History!$P$2:$P$5854,">=25",Fact_Snapshot_History!$P$2:$P$5854,"<=999",Fact_Snapshot_History!$R$2:$R$5854,1),"") | D19: =COUNTIFS(Fact_Snapshot_History!$P$2:$P$5854,">=25",Fact_Snapshot_History!$P$2:$P$5854,"<=999",Fact_Snapshot_History!$R$2:$R$5854,0) -> 443 | E19: =IFERROR(SUMIFS(Fact_Snapshot_History!$C$2:$C$5854,Fact_Snapshot_History!$P$2:$P$5854,">=25",Fact_Snapshot_History!$P$2:$P$5854,"<=999",Fact_Snapshot_History!$R$2:$R$5854,0,Fact_Snapshot_History!$G$2:$G$5854,1)/SUMIFS(Fact_Snapshot_History!$C$2:$C$5854,Fact_Snapshot_History!$P$2:$P$5854,">=25",Fact_Snapshot_History!$P$2:$P$5854,"<=999",Fact_Snapshot_History!$R$2:$R$5854,0),"") -> 0.031070003
A21: At this demonstration scale, individual age buckets carry small samples (n shown alongside every %) -- read the pooled comparison above as the primary result and this curve as directional/illustrative of shape, not a precise trend.

Sheet Collections_Effectiveness
A1: Collections Effectiveness
A2: United Winners DT SACCO, Nairobi -- SYNTHETIC demonstration data. Not United Winners' actual portfolio figures.
A3: Which contact channels convert, and where recovered cash actually comes from. Recovery per Contact = total linked recovery / total contacts on that channel (includes zero-recovery contacts, matching the validated SQL).
A5: By Collections Channel
A6: Channel | B6: Total Contacts | C6: Contact→Payment Conversion | D6: Recovery per Contact (Ksh)
A7: Phone Call | B7: =COUNTIF(Fact_Collections!$E$2:$E$187,"Phone Call") -> 84 | C7: =COUNTIFS(Fact_Collections!$E$2:$E$187,"Phone Call",Fact_Collections!$F$2:$F$187,"Payment Received")/$B7 -> 0.16666667 | D7: =SUMIF(Fact_Collections!$E$2:$E$187,"Phone Call",Fact_Collections!$G$2:$G$187)/$B7 -> 2406.5277
A8: SMS | B8: =COUNTIF(Fact_Collections!$E$2:$E$187,"SMS") -> 60 | C8: =COUNTIFS(Fact_Collections!$E$2:$E$187,"SMS",Fact_Collections!$F$2:$F$187,"Payment Received")/$B8 -> 0.15 | D8: =SUMIF(Fact_Collections!$E$2:$E$187,"SMS",Fact_Collections!$G$2:$G$187)/$B8 -> 2468.812
A9: In-Person Visit | B9: =COUNTIF(Fact_Collections!$E$2:$E$187,"In-Person Visit") -> 23 | C9: =COUNTIFS(Fact_Collections!$E$2:$E$187,"In-Person Visit",Fact_Collections!$F$2:$F$187,"Payment Received")/$B9 -> 0.13043478 | D9: =SUMIF(Fact_Collections!$E$2:$E$187,"In-Person Visit",Fact_Collections!$G$2:$G$187)/$B9 -> 1175.5635
A10: Restructuring Offer | B10: =COUNTIF(Fact_Collections!$E$2:$E$187,"Restructuring Offer") -> 9 | C10: =COUNTIFS(Fact_Collections!$E$2:$E$187,"Restructuring Offer",Fact_Collections!$F$2:$F$187,"Payment Received")/$B10 -> 0 | D10: =SUMIF(Fact_Collections!$E$2:$E$187,"Restructuring Offer",Fact_Collections!$G$2:$G$187)/$B10 -> 0
A11: Guarantor Contact | B11: =COUNTIF(Fact_Collections!$E$2:$E$187,"Guarantor Contact") -> 10 | C11: =COUNTIFS(Fact_Collections!$E$2:$E$187,"Guarantor Contact",Fact_Collections!$F$2:$F$187,"Payment Received")/$B11 -> 0.2 | D11: =SUMIF(Fact_Collections!$E$2:$E$187,"Guarantor Contact",Fact_Collections!$G$2:$G$187)/$B11 -> 2545.116
A13: Recovery Source Split
A14: Recovery Source | B14: Transactions | C14: Total Recovered (Ksh) | D14: % of Total Recovery
A15: Borrower Payment | B15: =COUNTIF(Fact_Recovery!$D$2:$D$37,"Borrower Payment") -> 20 | C15: =SUMIF(Fact_Recovery!$D$2:$D$37,"Borrower Payment",Fact_Recovery!$E$2:$E$37) -> 259285.16 | D15: =$C15/SUM(Fact_Recovery!$E$2:$E$37) -> 0.53684353
A16: Borrower Deposit | B16: =COUNTIF(Fact_Recovery!$D$2:$D$37,"Borrower Deposit") -> 11 | C16: =SUMIF(Fact_Recovery!$D$2:$D$37,"Borrower Deposit",Fact_Recovery!$E$2:$E$37) -> 128674.5 | D16: =$C16/SUM(Fact_Recovery!$E$2:$E$37) -> 0.26641738
A17: Guarantor Deposit | B17: =COUNTIF(Fact_Recovery!$D$2:$D$37,"Guarantor Deposit") -> 4 | C17: =SUMIF(Fact_Recovery!$D$2:$D$37,"Guarantor Deposit",Fact_Recovery!$E$2:$E$37) -> 77194.37 | D17: =$C17/SUM(Fact_Recovery!$E$2:$E$37) -> 0.15982904
A18: Other Recovery | B18: =COUNTIF(Fact_Recovery!$D$2:$D$37,"Other Recovery") -> 1 | C18: =SUMIF(Fact_Recovery!$D$2:$D$37,"Other Recovery",Fact_Recovery!$E$2:$E$37) -> 17826.85 | D18: =$C18/SUM(Fact_Recovery!$E$2:$E$37) -> 0.036910053

Sheet Q10_Savings_Behaviour
A1: Q10 — Savings Behaviour Ahead of Delinquency
A2: United Winners DT SACCO, Nairobi -- SYNTHETIC demonstration data. Not United Winners' actual portfolio figures.
A3: Descriptive/correlational only (per the validated SQL comments): does savings-contribution behaviour in the 2 months before a loan first goes 30+ days past due look different from members who never go delinquent? The matched comparison controls for calendar month; the unmatched baseline is reference-only and must never be called a control group.
A5: Populations Compared
A6: Population | B6: % Below Target or Missed | C6: n
A7: Treatment: pre-delinquency window (2mo before onset) | B7: =COUNTIFS(Fact_Q10!$A$2:$A$5739,"Treatment",Fact_Q10!$D$2:$D$5739,"<>Met")/$C7 -> 0.4887218 | C7: =COUNTIF(Fact_Q10!$A$2:$A$5739,"Treatment") -> 133
A8: Matched comparison: never-delinquent members, same calendar months | B8: =COUNTIFS(Fact_Q10!$A$2:$A$5739,"Matched comparison",Fact_Q10!$D$2:$D$5739,"<>Met")/$C8 -> 0.18180196 | C8: =COUNTIF(Fact_Q10!$A$2:$A$5739,"Matched comparison") -> 5605
A9: Unmatched baseline (reference only -- NOT a control group): all member-months | B9: =COUNTIF(Fact_Savings_Activity!$E$2:$E$13309,"<>Met")/$C9 -> 0.18905921 | C9: =COUNTA(Fact_Savings_Activity!$A$2:$A$13309) -> 13308
A11: Limitation, stated plainly (per the validated SQL): even the matched comparison is not a full matched control -- never-delinquent members may differ from the treatment group in ways beyond calendar timing (product mix, segment, risk profile).

Sheet Data_Quality
A1: Data Quality Checks
A2: United Winners DT SACCO, Nairobi -- SYNTHETIC demonstration data. Not United Winners' actual portfolio figures.
A3: Live checks re-run automatically whenever the embedded data changes. Mirrors the check families in qc_report.py (already validated at the SQL layer); duplicate-key/orphan checks against the 5,853-row snapshot history that would be expensive to brute-force as spreadsheet array formulas are noted as SQL-validated rather than re-run here -- see README.
A5: Referential Integrity
A6: Check | B6: Orphan / Violation Count | C6: Status
A7: Fact_Loans.product_id all exist in Dim_Products | B7: =SUMPRODUCT(--ISNA(MATCH(Fact_Loans!$C$2:$C$651,Dim_Products!$A$2:$A$14,0))) -> 0 | C7: =IF(B7=0,"PASS","FAIL") -> PASS
A8: Fact_Loans.member_id all exist in Dim_Members | B8: =SUMPRODUCT(--ISNA(MATCH(Fact_Loans!$B$2:$B$651,Dim_Members!$A$2:$A$354,0))) -> 0 | C8: =IF(B8=0,"PASS","FAIL") -> PASS
A9: Fact_Loans.branch_id all exist in Dim_Branches | B9: =SUMPRODUCT(--ISNA(MATCH(Fact_Loans!$D$2:$D$651,Dim_Branches!$A$2:$A$4,0))) -> 0 | C9: =IF(B9=0,"PASS","FAIL") -> PASS
A10: Fact_Snapshot_History.loan_id all exist in Fact_Loans | B10: =SUMPRODUCT(--ISNA(MATCH(Fact_Snapshot_History!$A$2:$A$5854,Fact_Loans!$A$2:$A$651,0))) -> 0 | C10: =IF(B10=0,"PASS","FAIL") -> PASS
A11: Fact_Loans: blank loan_id cells | B11: =COUNTBLANK(Fact_Loans!$A$2:$A$651) -> 0 | C11: =IF(B11=0,"PASS","FAIL") -> PASS
A13: Business-Rule Consistency
A14: Check | B14: Violation Count | C14: Status
A15: Outstanding balance never negative | B15: =SUMPRODUCT(--(Fact_Snapshot_History!$C$2:$C$5854<0)) -> 0 | C15: =IF(B15=0,"PASS","FAIL") -> PASS
A16: par30_flag=1 implies days_past_due>=30 | B16: =SUMPRODUCT((Fact_Snapshot_History!$G$2:$G$5854=1)*(Fact_Snapshot_History!$E$2:$E$5854<30)) -> 0 | C16: =IF(B16=0,"PASS","FAIL") -> PASS
A17: par60_flag=1 implies days_past_due>=60 | B17: =SUMPRODUCT((Fact_Snapshot_History!$H$2:$H$5854=1)*(Fact_Snapshot_History!$E$2:$E$5854<60)) -> 0 | C17: =IF(B17=0,"PASS","FAIL") -> PASS
A18: par90_flag=1 implies days_past_due>=90 | B18: =SUMPRODUCT((Fact_Snapshot_History!$I$2:$I$5854=1)*(Fact_Snapshot_History!$E$2:$E$5854<90)) -> 0 | C18: =IF(B18=0,"PASS","FAIL") -> PASS
A19: Monotonicity: par60_flag=1 implies par30_flag=1 | B19: =SUMPRODUCT((Fact_Snapshot_History!$H$2:$H$5854=1)*(Fact_Snapshot_History!$G$2:$G$5854=0)) -> 0 | C19: =IF(B19=0,"PASS","FAIL") -> PASS
A20: Monotonicity: par90_flag=1 implies par60_flag=1 | B20: =SUMPRODUCT((Fact_Snapshot_History!$I$2:$I$5854=1)*(Fact_Snapshot_History!$H$2:$H$5854=0)) -> 0 | C20: =IF(B20=0,"PASS","FAIL") -> PASS
A21: Recovery Rate is bounded at <=100% by construction | B21: =IF(KPI_Summary!$B$21<=1,0,1) -> 0 | C21: =IF(B21=0,"PASS","FAIL") -> PASS
A23: Primary-Key Uniqueness (small tables)
A24: Check | B24: Duplicate Count | C24: Status
A25: Dim_Products.product_id unique | B25: =COUNTA(Dim_Products!$A$2:$A$14)-SUMPRODUCT(1/COUNTIF(Dim_Products!$A$2:$A$14,Dim_Products!$A$2:$A$14)) -> 0 | C25: =IF(ROUND(B25,6)=0,"PASS","FAIL") -> PASS
A26: Dim_Branches.branch_id unique | B26: =COUNTA(Dim_Branches!$A$2:$A$4)-SUMPRODUCT(1/COUNTIF(Dim_Branches!$A$2:$A$4,Dim_Branches!$A$2:$A$4)) -> 0 | C26: =IF(ROUND(B26,6)=0,"PASS","FAIL") -> PASS
A27: Fact_Collection_Cases.loan_id unique (one case per loan) | B27: =COUNTA(Fact_Collection_Cases!$A$2:$A$105)-SUMPRODUCT(1/COUNTIF(Fact_Collection_Cases!$A$2:$A$105,Fact_Collection_Cases!$A$2:$A$105)) -> 0 | C27: =IF(ROUND(B27,6)=0,"PASS","FAIL") -> PASS
A28: Fact_Recovery.recovery_id unique | B28: =COUNTA(Fact_Recovery!$A$2:$A$37)-SUMPRODUCT(1/COUNTIF(Fact_Recovery!$A$2:$A$37,Fact_Recovery!$A$2:$A$37)) -> 0 | C28: =IF(ROUND(B28,6)=0,"PASS","FAIL") -> PASS
A30: Documented, Not Re-run Here
A31: Duplicate (loan_id, snapshot_date) key check and full FK sweeps across the 5,853-row Fact_Snapshot_History were validated in qc_report.py at the SQL layer (all PASS). Re-implementing them as spreadsheet array formulas would be an expensive, low-value duplication of already-validated logic -- a deliberate modelling choice, not an oversight.
A33: Table Row Counts (reference)
A34: Table | B34: Rows
A35: Dim_Products | B35: =COUNTA(Dim_Products!$A$2:$A$14) -> 13
A36: Dim_Members | B36: =COUNTA(Dim_Members!$A$2:$A$354) -> 353
A37: Dim_Branches | B37: =COUNTA(Dim_Branches!$A$2:$A$4) -> 3
A38: Fact_Loans | B38: =COUNTA(Fact_Loans!$A$2:$A$651) -> 650
A39: Fact_Snapshot_History | B39: =COUNTA(Fact_Snapshot_History!$A$2:$A$5854) -> 5853
A40: Fact_Collections | B40: =COUNTA(Fact_Collections!$A$2:$A$187) -> 186
A41: Fact_Recovery | B41: =COUNTA(Fact_Recovery!$A$2:$A$37) -> 36
A42: Fact_Collection_Cases | B42: =COUNTA(Fact_Collection_Cases!$A$2:$A$105) -> 104
A43: Fact_Arrears | B43: =COUNTA(Fact_Arrears!$A$2:$A$434) -> 433
A44: Fact_Q10 | B44: =COUNTA(Fact_Q10!$A$2:$A$5739) -> 5738
A45: Fact_Savings_Activity | B45: =COUNTA(Fact_Savings_Activity!$A$2:$A$13309) -> 13308

Sheet Dim_Products
A1: product_id | B1: product_name | C1: category | D1: typical_term_months | E1: typical_interest_rate_pm | F1: rate_source_note
A2: 1 | B2: Salary Advance | C2: FOSA | D2: 2 | E2: 1 | F2: ASSUMPTION - only the Ksh100,000 cap is verified
A3: 2 | B3: Jeki Loan | C3: FOSA | D3: 12 | E3: 1.5 | F3: ASSUMPTION - not publicly disclosed
A4: 3 | B4: Product Loan | C4: FOSA | D4: 12 | E4: 1.3 | F4: ASSUMPTION - not publicly disclosed
A5: 4 | B5: Mtumishi Loan | C5: FOSA | D5: 24 | E5: 1.2 | F5: ASSUMPTION - not publicly disclosed
A6: 5 | B6: School Fees Loan | C6: BOSA | D6: 4 | E6: 1.4 | F6: ASSUMPTION - not publicly disclosed
A7: 6 | B7: Bima Loan | C7: BOSA | D7: 12 | E7: 1.3 | F7: ASSUMPTION - not publicly disclosed
A8: 7 | B8: Development Loan | C8: BOSA | D8: 36 | E8: 1.2 | F8: ASSUMPTION - not publicly disclosed
A9: 8 | B9: Emergency Loan | C9: BOSA | D9: 6 | E9: 1.6 | F9: ASSUMPTION - not publicly disclosed
A10: 9 | B10: Instant Loan | C10: BOSA | D10: 3 | E10: 1.7 | F10: ASSUMPTION - not publicly disclosed
A11: 10 | B11: ELoan | C11: BOSA | D11: 6 | E11: 1.5 | F11: ASSUMPTION - not publicly disclosed
A12: 11 | B12: Moto Gari Loan | C12: BOSA | D12: 48 | E12: 1.1 | F12: ASSUMPTION - not publicly disclosed
A13: 12 | B13: Mjengo Loan | C13: BOSA | D13: 48 | E13: 1.1 | F13: ASSUMPTION - not publicly disclosed
A14: 13 | B14: Supa Loan | C14: BOSA | D14: 60 | E14: 1.1 | F14: VERIFIED - LinkedIn company page

Sheet Dim_Branches
A1: branch_id | B1: branch_name | C1: location_area
A2: 1 | B2: Headquarters | C2: Spine Road, Nairobi
A3: 2 | B3: Umoja | C3: Umoja, Nairobi
A4: 3 | B4: Ruai | C4: Ruai Mega Mall, Nairobi

Sheet Dim_Members
A1: member_id | B1: join_date | C1: branch_id | D1: member_segment | E1: employment_type | F1: employer_name | G1: share_capital_ksh | H1: monthly_savings_target_ksh | I1: member_status
A2: 1 | B2: 45386 | C2: 1 | D2: Individual | E2: Self-Employed | F2: Not Captured | G2: 18000 | H2: 1700 | I2: Active
A3: 2 | B3: 43322 | C3: 1 | D3: Individual | E3: Salaried-CheckOff | F3: Employer_013 | G3: 18500 | H3: 1600 | I3: Active
A4: 3 | B4: 45930 | C4: 1 | D4: Individual | E4: Self-Employed | F4: Not Captured | G4: 18500 | H4: 1550 | I4: Active
A5: 4 | B5: 43748 | C5: 3 | D5: Individual | E5: Salaried-CheckOff | F5: Employer_023 | G5: 18200 | H5: 1830 | I5: Active
A6: 5 | B6: 46147 | C6: 2 | D6: Individual | E6: Salaried-Direct | F6: Not Captured | G6: 19000 | H6: 1720 | I6: Dormant
A7: 6 | B7: 45255 | C7: 2 | D7: Individual | E7: Self-Employed | F7: Not Captured | G7: 18800 | H7: 1940 | I7: Dormant
A8: 7 | B8: 43926 | C8: 3 | D8: Individual | E8: Salaried-Direct | F8: Not Captured | G8: 17400 | H8: 1570 | I8: Active
A9: 8 | B9: 46206 | C9: 1 | D9: SME | E9: Salaried-CheckOff | F9: Employer_011 | G9: 17000 | H9: 1630 | I9: Active
A10: 9 | B10: 45188 | C10: 3 | D10: SME | E10: Self-Employed | F10: Not Captured | G10: 19000 | H10: 1820 | I10: Active
A11: 10 | B11: 43662 | C11: 1 | D11: Individual | E11: Salaried-CheckOff | F11: Employer_037 | G11: 17200 | H11: 1740 | I11: Active
A12: 11 | B12: 44249 | C12: 3 | D12: Individual | E12: Salaried-CheckOff | F12: Employer_036 | G12: 18700 | H12: 1610 | I12: Active
A13: 12 | B13: 42936 | C13: 1 | D13: Individual | E13: Salaried-CheckOff | F13: Employer_004 | G13: 16700 | H13: 1450 | I13: Active
... A354: 353 | B354: 45981 | C354: 1 | D354: Individual | E354: Self-Employed | F354: Not Captured | G354: 18100 | H354: 1750 | I354: Active

Sheet Fact_Loans
A1: loan_id | B1: member_id | C1: product_id | D1: branch_id | E1: disbursement_date | F1: principal_amount_ksh | G1: term_months | H1: interest_rate_pm | I1: repayment_channel | J1: guarantor_required | K1: product_name | L1: category | M1: member_segment | N1: branch_name
A2: 1 | B2: 141 | C2: 1 | D2: 2 | E2: 46069 | F2: 12800 | G2: 2 | H2: 1 | I2: Check-Off | J2: 0 | K2: =IFERROR(INDEX(Dim_Products!$B$2:$B$14,MATCH($C2,Dim_Products!$A$2:$A$14,0)),"") -> Salary Advance | L2: =IFERROR(INDEX(Dim_Products!$C$2:$C$14,MATCH($C2,Dim_Products!$A$2:$A$14,0)),"") -> FOSA | M2: =IFERROR(INDEX(Dim_Members!$D$2:$D$354,MATCH($B2,Dim_Members!$A$2:$A$354,0)),"") -> Learning Institution | N2: =IFERROR(INDEX(Dim_Branches!$B$2:$B$4,MATCH($D2,Dim_Branches!$A$2:$A$4,0)),"") -> Umoja
A3: 2 | B3: 321 | C3: 4 | D3: 3 | E3: 45994 | F3: 70100 | G3: 23 | H3: 1.2 | I3: Check-Off | J3: 0 | K3: =IFERROR(INDEX(Dim_Products!$B$2:$B$14,MATCH($C3,Dim_Products!$A$2:$A$14,0)),"") -> Mtumishi Loan | L3: =IFERROR(INDEX(Dim_Products!$C$2:$C$14,MATCH($C3,Dim_Products!$A$2:$A$14,0)),"") -> FOSA | M3: =IFERROR(INDEX(Dim_Members!$D$2:$D$354,MATCH($B3,Dim_Members!$A$2:$A$354,0)),"") -> Religious Institution | N3: =IFERROR(INDEX(Dim_Branches!$B$2:$B$4,MATCH($D3,Dim_Branches!$A$2:$A$4,0)),"") -> Ruai
A4: 3 | B4: 217 | C4: 8 | D4: 3 | E4: 45968 | F4: 9200 | G4: 5 | H4: 1.6 | I4: Direct-Standing-Order | J4: 0 | K4: =IFERROR(INDEX(Dim_Products!$B$2:$B$14,MATCH($C4,Dim_Products!$A$2:$A$14,0)),"") -> Emergency Loan | L4: =IFERROR(INDEX(Dim_Products!$C$2:$C$14,MATCH($C4,Dim_Products!$A$2:$A$14,0)),"") -> BOSA | M4: =IFERROR(INDEX(Dim_Members!$D$2:$D$354,MATCH($B4,Dim_Members!$A$2:$A$354,0)),"") -> SME | N4: =IFERROR(INDEX(Dim_Branches!$B$2:$B$4,MATCH($D4,Dim_Branches!$A$2:$A$4,0)),"") -> Ruai
A5: 4 | B5: 69 | C5: 8 | D5: 2 | E5: 45992 | F5: 4800 | G5: 5 | H5: 1.6 | I5: Direct-Standing-Order | J5: 0 | K5: =IFERROR(INDEX(Dim_Products!$B$2:$B$14,MATCH($C5,Dim_Products!$A$2:$A$14,0)),"") -> Emergency Loan | L5: =IFERROR(INDEX(Dim_Products!$C$2:$C$14,MATCH($C5,Dim_Products!$A$2:$A$14,0)),"") -> BOSA | M5: =IFERROR(INDEX(Dim_Members!$D$2:$D$354,MATCH($B5,Dim_Members!$A$2:$A$354,0)),"") -> Corporate | N5: =IFERROR(INDEX(Dim_Branches!$B$2:$B$4,MATCH($D5,Dim_Branches!$A$2:$A$4,0)),"") -> Umoja
A6: 5 | B6: 316 | C6: 8 | D6: 1 | E6: 45651 | F6: 27200 | G6: 5 | H6: 1.6 | I6: Direct-Standing-Order | J6: 0 | K6: =IFERROR(INDEX(Dim_Products!$B$2:$B$14,MATCH($C6,Dim_Products!$A$2:$A$14,0)),"") -> Emergency Loan | L6: =IFERROR(INDEX(Dim_Products!$C$2:$C$14,MATCH($C6,Dim_Products!$A$2:$A$14,0)),"") -> BOSA | M6: =IFERROR(INDEX(Dim_Members!$D$2:$D$354,MATCH($B6,Dim_Members!$A$2:$A$354,0)),"") -> Individual | N6: =IFERROR(INDEX(Dim_Branches!$B$2:$B$4,MATCH($D6,Dim_Branches!$A$2:$A$4,0)),"") -> Headquarters
A7: 6 | B7: 338 | C7: 10 | D7: 1 | E7: 45594 | F7: 32300 | G7: 7 | H7: 1.5 | I7: Direct-Standing-Order | J7: 0 | K7: =IFERROR(INDEX(Dim_Products!$B$2:$B$14,MATCH($C7,Dim_Products!$A$2:$A$14,0)),"") -> ELoan | L7: =IFERROR(INDEX(Dim_Products!$C$2:$C$14,MATCH($C7,Dim_Products!$A$2:$A$14,0)),"") -> BOSA | M7: =IFERROR(INDEX(Dim_Members!$D$2:$D$354,MATCH($B7,Dim_Members!$A$2:$A$354,0)),"") -> Corporate | N7: =IFERROR(INDEX(Dim_Branches!$B$2:$B$4,MATCH($D7,Dim_Branches!$A$2:$A$4,0)),"") -> Headquarters
A8: 7 | B8: 35 | C8: 1 | D8: 1 | E8: 45003 | F8: 92600 | G8: 1 | H8: 1 | I8: Cash-MobileMoney | J8: 0 | K8: =IFERROR(INDEX(Dim_Products!$B$2:$B$14,MATCH($C8,Dim_Products!$A$2:$A$14,0)),"") -> Salary Advance | L8: =IFERROR(INDEX(Dim_Products!$C$2:$C$14,MATCH($C8,Dim_Products!$A$2:$A$14,0)),"") -> FOSA | M8: =IFERROR(INDEX(Dim_Members!$D$2:$D$354,MATCH($B8,Dim_Members!$A$2:$A$354,0)),"") -> Individual | N8: =IFERROR(INDEX(Dim_Branches!$B$2:$B$4,MATCH($D8,Dim_Branches!$A$2:$A$4,0)),"") -> Headquarters
A9: 8 | B9: 147 | C9: 8 | D9: 2 | E9: 45588 | F9: 14400 | G9: 6 | H9: 1.6 | I9: Direct-Standing-Order | J9: 0 | K9: =IFERROR(INDEX(Dim_Products!$B$2:$B$14,MATCH($C9,Dim_Products!$A$2:$A$14,0)),"") -> Emergency Loan | L9: =IFERROR(INDEX(Dim_Products!$C$2:$C$14,MATCH($C9,Dim_Products!$A$2:$A$14,0)),"") -> BOSA | M9: =IFERROR(INDEX(Dim_Members!$D$2:$D$354,MATCH($B9,Dim_Members!$A$2:$A$354,0)),"") -> Individual | N9: =IFERROR(INDEX(Dim_Branches!$B$2:$B$4,MATCH($D9,Dim_Branches!$A$2:$A$4,0)),"") -> Umoja
A10: 9 | B10: 80 | C10: 7 | D10: 2 | E10: 45362 | F10: 335400 | G10: 37 | H10: 1.2 | I10: Cash-MobileMoney | J10: 1 | K10: =IFERROR(INDEX(Dim_Products!$B$2:$B$14,MATCH($C10,Dim_Products!$A$2:$A$14,0)),"") -> Development Loan | L10: =IFERROR(INDEX(Dim_Products!$C$2:$C$14,MATCH($C10,Dim_Products!$A$2:$A$14,0)),"") -> BOSA | M10: =IFERROR(INDEX(Dim_Members!$D$2:$D$354,MATCH($B10,Dim_Members!$A$2:$A$354,0)),"") -> Individual | N10: =IFERROR(INDEX(Dim_Branches!$B$2:$B$4,MATCH($D10,Dim_Branches!$A$2:$A$4,0)),"") -> Umoja
A11: 10 | B11: 185 | C11: 1 | D11: 1 | E11: 46262 | F11: 39900 | G11: 1 | H11: 1 | I11: Direct-Standing-Order | J11: 0 | K11: =IFERROR(INDEX(Dim_Products!$B$2:$B$14,MATCH($C11,Dim_Products!$A$2:$A$14,0)),"") -> Salary Advance | L11: =IFERROR(INDEX(Dim_Products!$C$2:$C$14,MATCH($C11,Dim_Products!$A$2:$A$14,0)),"") -> FOSA | M11: =IFERROR(INDEX(Dim_Members!$D$2:$D$354,MATCH($B11,Dim_Members!$A$2:$A$354,0)),"") -> Corporate | N11: =IFERROR(INDEX(Dim_Branches!$B$2:$B$4,MATCH($D11,Dim_Branches!$A$2:$A$4,0)),"") -> Headquarters
A12: 11 | B12: 53 | C12: 10 | D12: 1 | E12: 45942 | F12: 10200 | G12: 7 | H12: 1.5 | I12: Cash-MobileMoney | J12: 0 | K12: =IFERROR(INDEX(Dim_Products!$B$2:$B$14,MATCH($C12,Dim_Products!$A$2:$A$14,0)),"") -> ELoan | L12: =IFERROR(INDEX(Dim_Products!$C$2:$C$14,MATCH($C12,Dim_Products!$A$2:$A$14,0)),"") -> BOSA | M12: =IFERROR(INDEX(Dim_Members!$D$2:$D$354,MATCH($B12,Dim_Members!$A$2:$A$354,0)),"") -> Individual | N12: =IFERROR(INDEX(Dim_Branches!$B$2:$B$4,MATCH($D12,Dim_Branches!$A$2:$A$4,0)),"") -> Headquarters
A13: 12 | B13: 265 | C13: 13 | D13: 3 | E13: 45742 | F13: 444600 | G13: 59 | H13: 1.1 | I13: Direct-Standing-Order | J13: 1 | K13: =IFERROR(INDEX(Dim_Products!$B$2:$B$14,MATCH($C13,Dim_Products!$A$2:$A$14,0)),"") -> Supa Loan | L13: =IFERROR(INDEX(Dim_Products!$C$2:$C$14,MATCH($C13,Dim_Products!$A$2:$A$14,0)),"") -> BOSA | M13: =IFERROR(INDEX(Dim_Members!$D$2:$D$354,MATCH($B13,Dim_Members!$A$2:$A$354,0)),"") -> Individual | N13: =IFERROR(INDEX(Dim_Branches!$B$2:$B$4,MATCH($D13,Dim_Branches!$A$2:$A$4,0)),"") -> Ruai
... A651: 650 | B651: 9 | C651: 2 | D651: 3 | E651: 45489 | F651: 43900 | G651: 12 | H651: 1.5 | I651: Cash-MobileMoney | J651: 0 | K651: =IFERROR(INDEX(Dim_Products!$B$2:$B$14,MATCH($C651,Dim_Products!$A$2:$A$14,0)),"") -> Jeki Loan | L651: =IFERROR(INDEX(Dim_Products!$C$2:$C$14,MATCH($C651,Dim_Products!$A$2:$A$14,0)),"") -> FOSA | M651: =IFERROR(INDEX(Dim_Members!$D$2:$D$354,MATCH($B651,Dim_Members!$A$2:$A$354,0)),"") -> SME | N651: =IFERROR(INDEX(Dim_Branches!$B$2:$B$4,MATCH($D651,Dim_Branches!$A$2:$A$4,0)),"") -> Ruai

Sheet Fact_Snapshot_History
A1: loan_id | B1: snapshot_date | C1: outstanding_balance_ksh | D1: amount_overdue_ksh | E1: days_past_due | F1: classification | G1: par30_flag | H1: par60_flag | I1: par90_flag | J1: member_id | K1: product_id | L1: branch_id | M1: repayment_channel | N1: member_segment | O1: disbursement_date | P1: months_on_book | Q1: year_month | R1: is_seeded_weak_vintage
A2: 1 | B2: 46081 | C2: 12800 | D2: 0 | E2: 0 | F2: Normal | G2: 0 | H2: 0 | I2: 0 | J2: 141 | K2: 1 | L2: 2 | M2: Check-Off | N2: Learning Institution | O2: 46069 | P2: =ROUNDDOWN(($B2-$O2)/30,0) -> 0 | Q2: =TEXT($B2,"yyyy-mm") -> 2026-02 | R2: =IF(AND($O2>=DATE(2025,1,1),$O2<=DATE(2025,4,30)),1,0) -> 0
A3: 1 | B3: 46112 | C3: 6400 | D3: 0 | E3: 0 | F3: Normal | G3: 0 | H3: 0 | I3: 0 | J3: 141 | K3: 1 | L3: 2 | M3: Check-Off | N3: Learning Institution | O3: 46069 | P3: =ROUNDDOWN(($B3-$O3)/30,0) -> 1 | Q3: =TEXT($B3,"yyyy-mm") -> 2026-03 | R3: =IF(AND($O3>=DATE(2025,1,1),$O3<=DATE(2025,4,30)),1,0) -> 0
A4: 1 | B4: 46142 | C4: 0 | D4: 0 | E4: 0 | F4: Normal | G4: 0 | H4: 0 | I4: 0 | J4: 141 | K4: 1 | L4: 2 | M4: Check-Off | N4: Learning Institution | O4: 46069 | P4: =ROUNDDOWN(($B4-$O4)/30,0) -> 2 | Q4: =TEXT($B4,"yyyy-mm") -> 2026-04 | R4: =IF(AND($O4>=DATE(2025,1,1),$O4<=DATE(2025,4,30)),1,0) -> 0
A5: 2 | B5: 46022 | C5: 70100 | D5: 0 | E5: 0 | F5: Normal | G5: 0 | H5: 0 | I5: 0 | J5: 321 | K5: 4 | L5: 3 | M5: Check-Off | N5: Religious Institution | O5: 45994 | P5: =ROUNDDOWN(($B5-$O5)/30,0) -> 0 | Q5: =TEXT($B5,"yyyy-mm") -> 2025-12 | R5: =IF(AND($O5>=DATE(2025,1,1),$O5<=DATE(2025,4,30)),1,0) -> 0
A6: 2 | B6: 46053 | C6: 67052.17 | D6: 0 | E6: 0 | F6: Normal | G6: 0 | H6: 0 | I6: 0 | J6: 321 | K6: 4 | L6: 3 | M6: Check-Off | N6: Religious Institution | O6: 45994 | P6: =ROUNDDOWN(($B6-$O6)/30,0) -> 1 | Q6: =TEXT($B6,"yyyy-mm") -> 2026-01 | R6: =IF(AND($O6>=DATE(2025,1,1),$O6<=DATE(2025,4,30)),1,0) -> 0
A7: 2 | B7: 46081 | C7: 64004.34 | D7: 0 | E7: 0 | F7: Normal | G7: 0 | H7: 0 | I7: 0 | J7: 321 | K7: 4 | L7: 3 | M7: Check-Off | N7: Religious Institution | O7: 45994 | P7: =ROUNDDOWN(($B7-$O7)/30,0) -> 2 | Q7: =TEXT($B7,"yyyy-mm") -> 2026-02 | R7: =IF(AND($O7>=DATE(2025,1,1),$O7<=DATE(2025,4,30)),1,0) -> 0
A8: 2 | B8: 46112 | C8: 60956.51 | D8: 0 | E8: 0 | F8: Normal | G8: 0 | H8: 0 | I8: 0 | J8: 321 | K8: 4 | L8: 3 | M8: Check-Off | N8: Religious Institution | O8: 45994 | P8: =ROUNDDOWN(($B8-$O8)/30,0) -> 3 | Q8: =TEXT($B8,"yyyy-mm") -> 2026-03 | R8: =IF(AND($O8>=DATE(2025,1,1),$O8<=DATE(2025,4,30)),1,0) -> 0
A9: 2 | B9: 46142 | C9: 57908.68 | D9: 0 | E9: 0 | F9: Normal | G9: 0 | H9: 0 | I9: 0 | J9: 321 | K9: 4 | L9: 3 | M9: Check-Off | N9: Religious Institution | O9: 45994 | P9: =ROUNDDOWN(($B9-$O9)/30,0) -> 4 | Q9: =TEXT($B9,"yyyy-mm") -> 2026-04 | R9: =IF(AND($O9>=DATE(2025,1,1),$O9<=DATE(2025,4,30)),1,0) -> 0
A10: 2 | B10: 46173 | C10: 54860.85 | D10: 0 | E10: 0 | F10: Normal | G10: 0 | H10: 0 | I10: 0 | J10: 321 | K10: 4 | L10: 3 | M10: Check-Off | N10: Religious Institution | O10: 45994 | P10: =ROUNDDOWN(($B10-$O10)/30,0) -> 5 | Q10: =TEXT($B10,"yyyy-mm") -> 2026-05 | R10: =IF(AND($O10>=DATE(2025,1,1),$O10<=DATE(2025,4,30)),1,0) -> 0
A11: 2 | B11: 46203 | C11: 51813.02 | D11: 0 | E11: 0 | F11: Normal | G11: 0 | H11: 0 | I11: 0 | J11: 321 | K11: 4 | L11: 3 | M11: Check-Off | N11: Religious Institution | O11: 45994 | P11: =ROUNDDOWN(($B11-$O11)/30,0) -> 6 | Q11: =TEXT($B11,"yyyy-mm") -> 2026-06 | R11: =IF(AND($O11>=DATE(2025,1,1),$O11<=DATE(2025,4,30)),1,0) -> 0
A12: 2 | B12: 46234 | C12: 48765.19 | D12: 0 | E12: 0 | F12: Normal | G12: 0 | H12: 0 | I12: 0 | J12: 321 | K12: 4 | L12: 3 | M12: Check-Off | N12: Religious Institution | O12: 45994 | P12: =ROUNDDOWN(($B12-$O12)/30,0) -> 8 | Q12: =TEXT($B12,"yyyy-mm") -> 2026-07 | R12: =IF(AND($O12>=DATE(2025,1,1),$O12<=DATE(2025,4,30)),1,0) -> 0
A13: 2 | B13: 46265 | C13: 45717.36 | D13: 0 | E13: 0 | F13: Normal | G13: 0 | H13: 0 | I13: 0 | J13: 321 | K13: 4 | L13: 3 | M13: Check-Off | N13: Religious Institution | O13: 45994 | P13: =ROUNDDOWN(($B13-$O13)/30,0) -> 9 | Q13: =TEXT($B13,"yyyy-mm") -> 2026-08 | R13: =IF(AND($O13>=DATE(2025,1,1),$O13<=DATE(2025,4,30)),1,0) -> 0
... A5854: 650 | B5854: 45869 | C5854: 0.04 | D5854: 0 | E5854: 0 | F5854: Normal | G5854: 0 | H5854: 0 | I5854: 0 | J5854: 9 | K5854: 2 | L5854: 3 | M5854: Cash-MobileMoney | N5854: SME | O5854: 45489 | P5854: =ROUNDDOWN(($B5854-$O5854)/30,0) -> 12 | Q5854: =TEXT($B5854,"yyyy-mm") -> 2025-07 | R5854: =IF(AND($O5854>=DATE(2025,1,1),$O5854<=DATE(2025,4,30)),1,0) -> 0

Sheet Fact_Collections
A1: activity_id | B1: loan_id | C1: officer_id | D1: activity_date | E1: channel | F1: outcome | G1: linked_recovery_ksh | H1: resulted_in_payment
A2: 1 | B2: 6 | C2: 6 | D2: 45716 | E2: SMS | F2: No Contact | G2: 0 | H2: 0
A3: 2 | B3: 11 | C3: 3 | D3: 46034 | E3: Phone Call | F3: Payment Received | G3: 3677.19 | H3: 1
A4: 3 | B4: 30 | C4: 6 | D4: 46016 | E4: Phone Call | F4: No Contact | G4: 0 | H4: 0
A5: 4 | B5: 30 | C5: 2 | D5: 46078 | E5: Guarantor Contact | F5: Payment Received | G5: 15458.85 | H5: 1
A6: 5 | B6: 44 | C6: 4 | D6: 45372 | E6: Phone Call | F6: Disputed | G6: 0 | H6: 0
A7: 6 | B7: 44 | C7: 4 | D7: 45403 | E7: Guarantor Contact | F7: Disputed | G7: 0 | H7: 0
A8: 7 | B8: 45 | C8: 6 | D8: 45639 | E8: Phone Call | F8: No Contact | G8: 0 | H8: 0
A9: 8 | B9: 62 | C9: 3 | D9: 46174 | E9: SMS | F9: Promise-to-Pay | G9: 0 | H9: 0
A10: 9 | B10: 62 | C10: 3 | D10: 46204 | E10: SMS | F10: Payment Received | G10: 34225.71 | H10: 1
A11: 10 | B11: 63 | C11: 6 | D11: 45013 | E11: SMS | F11: Refused | G11: 0 | H11: 0
A12: 11 | B12: 63 | C12: 3 | D12: 45044 | E12: SMS | F12: Refused | G12: 0 | H12: 0
A13: 12 | B13: 63 | C13: 3 | D13: 45166 | E13: SMS | F13: Payment Received | G13: 22982.3 | H13: 1
... A187: 186 | B187: 648 | C187: 6 | D187: 45585 | E187: SMS | F187: No Contact | G187: 0 | H187: 0

Sheet Fact_Recovery
A1: recovery_id | B1: loan_id | C1: recovery_date | D1: recovery_source | E1: amount_recovered_ksh | F1: related_activity_id
A2: 1 | B2: 11 | C2: 46065 | D2: Borrower Payment | E2: 3677.19 | F2: 2
A3: 2 | B3: 23 | C3: 45133 | D3: Borrower Deposit | E3: 10074.94
A4: 3 | B4: 30 | C4: 46078 | D4: Borrower Deposit | E4: 15458.85 | F4: 4
A5: 4 | B5: 62 | C5: 46235 | D5: Borrower Payment | E5: 34225.71 | F5: 9
A6: 5 | B6: 63 | C6: 45166 | D6: Borrower Deposit | E6: 22982.3 | F6: 12
A7: 6 | B7: 70 | C7: 45964 | D7: Borrower Payment | E7: 59046.11 | F7: 14
A8: 7 | B8: 105 | C8: 45783 | D8: Guarantor Deposit | E8: 4468.29 | F8: 26
A9: 8 | B9: 136 | C9: 46162 | D9: Borrower Payment | E9: 9992.31 | F9: 34
A10: 9 | B10: 150 | C10: 45636 | D10: Guarantor Deposit | E10: 28179.22 | F10: 42
A11: 10 | B11: 151 | C11: 45130 | D11: Borrower Payment | E11: 10880.51 | F11: 43
A12: 11 | B12: 165 | C12: 46041 | D12: Borrower Payment | E12: 3355.26 | F12: 45
A13: 12 | B13: 172 | C13: 46088 | D13: Borrower Payment | E13: 11600
A14: 13 | B14: 174 | C14: 45501 | D14: Borrower Deposit | E14: 10158.78 | F14: 47
A15: 14 | B15: 214 | C15: 45728 | D15: Borrower Payment | E15: 1611.47
A16: 15 | B16: 216 | C16: 45559 | D16: Borrower Deposit | E16: 10785.26 | F16: 56
A17: 16 | B17: 226 | C17: 46102 | D17: Borrower Payment | E17: 7087.64 | F17: 63
A18: 17 | B18: 231 | C18: 46254 | D18: Borrower Payment | E18: 2394.81 | F18: 64
A19: 18 | B19: 248 | C19: 45611 | D19: Borrower Deposit | E19: 10475.01 | F19: 70
A20: 19 | B20: 277 | C20: 46047 | D20: Borrower Deposit | E20: 3833.32 | F20: 73
A21: 20 | B21: 278 | C21: 45341 | D21: Borrower Payment | E21: 2484.38 | F21: 74
A22: 21 | B22: 284 | C22: 45566 | D22: Borrower Payment | E22: 9243.42 | F22: 79
A23: 22 | B23: 328 | C23: 45797 | D23: Other Recovery | E23: 17826.85 | F23: 90
A24: 23 | B24: 363 | C24: 44966 | D24: Borrower Payment | E24: 7750 | F24: 101
A25: 24 | B25: 396 | C25: 45818 | D25: Borrower Deposit | E25: 4278.3 | F25: 117
A26: 25 | B26: 407 | C26: 46090 | D26: Borrower Payment | E26: 4355.18
A27: 26 | B27: 421 | C27: 45778 | D27: Borrower Payment | E27: 31258.85 | F27: 120
A28: 27 | B28: 464 | C28: 46043 | D28: Borrower Deposit | E28: 12604.41
A29: 28 | B29: 465 | C29: 45697 | D29: Borrower Payment | E29: 6642.87 | F29: 136
A30: 29 | B30: 489 | C30: 46204 | D30: Borrower Payment | E30: 7858.27 | F30: 142
A31: 30 | B31: 513 | C31: 46201 | D31: Borrower Deposit | E31: 21373.32
A32: 31 | B32: 535 | C32: 45532 | D32: Guarantor Deposit | E32: 22388.09 | F32: 156
A33: 32 | B33: 564 | C33: 45725 | D33: Guarantor Deposit | E33: 22158.77 | F33: 162
A34: 33 | B34: 582 | C34: 45258 | D34: Borrower Payment | E34: 16520
A35: 34 | B35: 583 | C35: 46211 | D35: Borrower Payment | E35: 2075.39
A36: 35 | B36: 584 | C36: 45431 | D36: Borrower Deposit | E36: 6650.01 | F36: 168
A37: 36 | B37: 588 | C37: 45433 | D37: Borrower Payment | E37: 27225.79 | F37: 173

Sheet Fact_Collection_Cases
A1: loan_id | B1: case_open_date | C1: case_close_date | D1: referred_amount_ksh | E1: recovered_in_window_ksh
A2: 5 | B2: 45808 | C2: 45992 | D2: 8139.35 | E2: 0
A3: 6 | B3: 45688 | C3: 45869 | D3: 23516.92 | E3: 0
A4: 11 | B4: 46053 | C4: 46234 | D4: 3677.19 | E4: 3677.19
A5: 13 | B5: 46265 | C5: 46449 | D5: 21847.97 | E5: 0
A6: 18 | B6: 45747 | C6: 45931 | D6: 5983.34 | E6: 0
A7: 23 | B7: 45107 | C7: 45290 | D7: 10074.94 | E7: 10074.94
A8: 30 | B8: 45991 | C8: 46172 | D8: 15458.85 | E8: 15458.85
A9: 44 | B9: 45412 | C9: 45595 | D9: 21188.75 | E9: 0
A10: 45 | B10: 45688 | C10: 45869 | D10: 5461.12 | E10: 0
A11: 62 | B11: 46234 | C11: 46418 | D11: 34225.71 | E11: 34225.71
A12: 63 | B12: 45046 | C12: 45229 | D12: 22982.3 | E12: 22982.3
A13: 70 | B13: 45930 | C13: 46111 | D13: 59046.11 | E13: 59046.11
... A105: 648 | B105: 45596 | C105: 45778 | D105: 18446.68 | E105: 0

Sheet Fact_Arrears
A1: loan_id | B1: period | C1: derived_source | D1: shortfall_ksh
A2: 45 | B2: 45639 | C2: Employer/check-off remittance shortfall | D2: 1427.79
A3: 45 | B3: 45670 | C3: Employer/check-off remittance shortfall | D3: 4033.33
A4: 89 | B4: 45771 | C4: Employer/check-off remittance shortfall | D4: 1101.59
A5: 89 | B5: 45801 | C5: Employer/check-off remittance shortfall | D5: 1179.54
A6: 89 | B6: 45832 | C6: Employer/check-off remittance shortfall | D6: 1033.17
A7: 113 | B7: 44770 | C7: Employer/check-off remittance shortfall | D7: 908.09
A8: 113 | B8: 44801 | C8: Employer/check-off remittance shortfall | D8: 1700
A9: 135 | B9: 45009 | C9: Employer/check-off remittance shortfall | D9: 2310.13
A10: 135 | B10: 45040 | C10: Employer/check-off remittance shortfall | D10: 954.02
A11: 135 | B11: 45070 | C11: Employer/check-off remittance shortfall | D11: 2983.33
A12: 137 | B12: 45398 | C12: Employer/check-off remittance shortfall | D12: 15566.67
A13: 137 | B13: 45428 | C13: Employer/check-off remittance shortfall | D13: 7557.78
... A434: 648 | B434: 45828 | C434: Direct/member-side repayment shortfall | D434: 2718.18

Sheet Fact_Q10
A1: population | B1: member_id | C1: period | D1: contribution_status
A2: Treatment | B2: 316 | C2: 45747 | D2: Missed
A3: Treatment | B3: 316 | C3: 45777 | D3: Met
A4: Treatment | B4: 338 | C4: 45657 | D4: Met
A5: Treatment | B5: 53 | C5: 46022 | D5: Met
A6: Treatment | B6: 5 | C6: 46234 | D6: Met
A7: Treatment | B7: 67 | C7: 45688 | D7: Missed
A8: Treatment | B8: 67 | C8: 45716 | D8: Met
A9: Treatment | B9: 29 | C9: 45046 | D9: Met
A10: Treatment | B10: 60 | C10: 45930 | D10: Met
A11: Treatment | B11: 87 | C11: 45657 | D11: Met
A12: Treatment | B12: 302 | C12: 46173 | D12: Missed
A13: Treatment | B13: 302 | C13: 46203 | D13: Met
... A5739: Matched Comparison | B5739: 352 | C5739: 46234 | D5739: Met

Sheet Fact_Savings_Activity
A1: member_id | B1: period | C1: savings_balance_ksh | D1: monthly_contribution_ksh | E1: contribution_status
A2: 1 | B2: 45412 | C2: 6563.35 | D2: 1700 | E2: Met
A3: 1 | B3: 45443 | C3: 8072.59 | D3: 1700 | E3: Met
A4: 1 | B4: 45473 | C4: 9308.8 | D4: 1700 | E4: Met
A5: 1 | B5: 45504 | C5: 10350.25 | D5: 1081.3 | E5: Below-Target
A6: 1 | B6: 45535 | C6: 11631.49 | D6: 1700 | E6: Met
A7: 1 | B7: 45565 | C7: 13310.82 | D7: 1700 | E7: Met
A8: 1 | B8: 45596 | C8: 12878.76 | D8: 0 | E8: Missed
A9: 1 | B9: 45626 | C9: 14409.72 | D9: 1700 | E9: Met
A10: 1 | B10: 45657 | C10: 15851.29 | D10: 1700 | E10: Met
A11: 1 | B11: 45688 | C11: 17499.63 | D11: 1700 | E11: Met
A12: 1 | B12: 45716 | C12: 18913.22 | D12: 1700 | E12: Met
A13: 1 | B13: 45747 | C13: 20353.37 | D13: 1700 | E13: Met
... A13309: 353 | B13309: 46265 | C13309: 24280.5 | D13309: 0 | E13309: Missed
